{
 "documentInfo": {
  "documentType": "https://xbrl.org/2021/xbrl-json",
  "features": {
   "xbrl:canonicalValues": true
  },
  "namespaces": {
   "cey": "http://www.centamin.com/20211231",
   "ifrs-full": "http://xbrl.ifrs.org/taxonomy/2020-03-16/ifrs-full",
   "iso4217": "http://www.xbrl.org/2003/iso4217",
   "scheme": "http://standards.iso.org/iso/17442",
   "xbrl": "https://xbrl.org/2021",
   "xbrli": "http://www.xbrl.org/2003/instance"
  },
  "taxonomy": [
   "http://www.centamin.com/xbrl/2021/213800PDI9G7OUKLPV84-2021-12-31.xsd"
  ]
 },
 "facts": {
  "f44127": {
   "value": "956217000",
   "decimals": -3,
   "dimensions": {
    "concept": "ifrs-full:PropertyPlantAndEquipment",
    "entity": "scheme:213800PDI9G7OUKLPV84",
    "period": "2022-01-01T00:00:00",
    "unit": "iso4217:USD"
   }
  },
  "f44132": {
   "value": "829884000",
   "decimals": -3,
   "dimensions": {
    "concept": "ifrs-full:PropertyPlantAndEquipment",
    "entity": "scheme:213800PDI9G7OUKLPV84",
    "period": "2021-01-01T00:00:00",
    "unit": "iso4217:USD"
   }
  },
  "f44141": {
   "value": "25261000",
   "decimals": -3,
   "dimensions": {
    "concept": "ifrs-full:TangibleExplorationAndEvaluationAssets",
    "entity": "scheme:213800PDI9G7OUKLPV84",
    "period": "2022-01-01T00:00:00",
    "unit": "iso4217:USD"
   }
  },
  "f44146": {
   "value": "63701000",
   "decimals": -3,
   "dimensions": {
    "concept": "ifrs-full:TangibleExplorationAndEvaluationAssets",
    "entity": "scheme:213800PDI9G7OUKLPV84",
    "period": "2021-01-01T00:00:00",
    "unit": "iso4217:USD"
   }
  },
  "f44156": {
   "value": "64756000",
   "decimals": -3,
   "dimensions": {
    "concept": "ifrs-full:NoncurrentOreStockpiles",
    "entity": "scheme:213800PDI9G7OUKLPV84",
    "period": "2022-01-01T00:00:00",
    "unit": "iso4217:USD"
   }
  },
  "f44162": {
   "value": "64870000",
   "decimals": -3,
   "dimensions": {
    "concept": "ifrs-full:NoncurrentOreStockpiles",
    "entity": "scheme:213800PDI9G7OUKLPV84",
    "period": "2021-01-01T00:00:00",
    "unit": "iso4217:USD"
   }
  },
  "f44171": {
   "value": "101000",
   "decimals": -3,
   "dimensions": {
    "concept": "ifrs-full:OtherNoncurrentReceivables",
    "entity": "scheme:213800PDI9G7OUKLPV84",
    "period": "2022-01-01T00:00:00",
    "unit": "iso4217:USD"
   }
  },
  "f44175": {
   "value": "103000",
   "decimals": -3,
   "dimensions": {
    "concept": "ifrs-full:OtherNoncurrentReceivables",
    "entity": "scheme:213800PDI9G7OUKLPV84",
    "period": "2021-01-01T00:00:00",
    "unit": "iso4217:USD"
   }
  },
  "f44182": {
   "value": "1046335000",
   "decimals": -3,
   "dimensions": {
    "concept": "ifrs-full:NoncurrentAssets",
    "entity": "scheme:213800PDI9G7OUKLPV84",
    "period": "2022-01-01T00:00:00",
    "unit": "iso4217:USD"
   }
  },
  "f44188": {
   "value": "958558000",
   "decimals": -3,
   "dimensions": {
    "concept": "ifrs-full:NoncurrentAssets",
    "entity": "scheme:213800PDI9G7OUKLPV84",
    "period": "2021-01-01T00:00:00",
    "unit": "iso4217:USD"
   }
  },
  "f44197": {
   "value": "128721000",
   "decimals": -3,
   "dimensions": {
    "concept": "ifrs-full:CurrentOreStockpiles",
    "entity": "scheme:213800PDI9G7OUKLPV84",
    "period": "2022-01-01T00:00:00",
    "unit": "iso4217:USD"
   }
  },
  "f44204": {
   "value": "118705000",
   "decimals": -3,
   "dimensions": {
    "concept": "ifrs-full:CurrentOreStockpiles",
    "entity": "scheme:213800PDI9G7OUKLPV84",
    "period": "2021-01-01T00:00:00",
    "unit": "iso4217:USD"
   }
  },
  "f44215": {
   "value": "32579000",
   "decimals": -3,
   "dimensions": {
    "concept": "ifrs-full:TradeAndOtherCurrentReceivables",
    "entity": "scheme:213800PDI9G7OUKLPV84",
    "period": "2022-01-01T00:00:00",
    "unit": "iso4217:USD"
   }
  },
  "f44219": {
   "value": "18424000",
   "decimals": -3,
   "dimensions": {
    "concept": "ifrs-full:TradeAndOtherCurrentReceivables",
    "entity": "scheme:213800PDI9G7OUKLPV84",
    "period": "2021-01-01T00:00:00",
    "unit": "iso4217:USD"
   }
  },
  "f44227": {
   "value": "7964000",
   "decimals": -3,
   "dimensions": {
    "concept": "ifrs-full:CurrentPrepayments",
    "entity": "scheme:213800PDI9G7OUKLPV84",
    "period": "2022-01-01T00:00:00",
    "unit": "iso4217:USD"
   }
  },
  "f44234": {
   "value": "8908000",
   "decimals": -3,
   "dimensions": {
    "concept": "ifrs-full:CurrentPrepayments",
    "entity": "scheme:213800PDI9G7OUKLPV84",
    "period": "2021-01-01T00:00:00",
    "unit": "iso4217:USD"
   }
  },
  "f44243": {
   "value": "207821000",
   "decimals": -3,
   "dimensions": {
    "concept": "ifrs-full:CashAndCashEquivalents",
    "entity": "scheme:213800PDI9G7OUKLPV84",
    "period": "2022-01-01T00:00:00",
    "unit": "iso4217:USD"
   }
  },
  "f44252": {
   "value": "291281000",
   "decimals": -3,
   "dimensions": {
    "concept": "ifrs-full:CashAndCashEquivalents",
    "entity": "scheme:213800PDI9G7OUKLPV84",
    "period": "2021-01-01T00:00:00",
    "unit": "iso4217:USD"
   }
  },
  "f44261": {
   "value": "377085000",
   "decimals": -3,
   "dimensions": {
    "concept": "ifrs-full:CurrentAssets",
    "entity": "scheme:213800PDI9G7OUKLPV84",
    "period": "2022-01-01T00:00:00",
    "unit": "iso4217:USD"
   }
  },
  "f44270": {
   "value": "437318000",
   "decimals": -3,
   "dimensions": {
    "concept": "ifrs-full:CurrentAssets",
    "entity": "scheme:213800PDI9G7OUKLPV84",
    "period": "2021-01-01T00:00:00",
    "unit": "iso4217:USD"
   }
  },
  "f44280": {
   "value": "1423420000",
   "decimals": -3,
   "dimensions": {
    "concept": "ifrs-full:Assets",
    "entity": "scheme:213800PDI9G7OUKLPV84",
    "period": "2022-01-01T00:00:00",
    "unit": "iso4217:USD"
   }
  },
  "f44286": {
   "value": "1395876000",
   "decimals": -3,
   "dimensions": {
    "concept": "ifrs-full:Assets",
    "entity": "scheme:213800PDI9G7OUKLPV84",
    "period": "2021-01-01T00:00:00",
    "unit": "iso4217:USD"
   }
  },
  "f44296": {
   "value": "42647000",
   "decimals": -3,
   "dimensions": {
    "concept": "ifrs-full:NoncurrentProvisions",
    "entity": "scheme:213800PDI9G7OUKLPV84",
    "period": "2022-01-01T00:00:00",
    "unit": "iso4217:USD"
   }
  },
  "f44301": {
   "value": "32752000",
   "decimals": -3,
   "dimensions": {
    "concept": "ifrs-full:NoncurrentProvisions",
    "entity": "scheme:213800PDI9G7OUKLPV84",
    "period": "2021-01-01T00:00:00",
    "unit": "iso4217:USD"
   }
  },
  "f44309": {
   "value": "10386000",
   "decimals": -3,
   "dimensions": {
    "concept": "ifrs-full:OtherNoncurrentPayables",
    "entity": "scheme:213800PDI9G7OUKLPV84",
    "period": "2022-01-01T00:00:00",
    "unit": "iso4217:USD"
   }
  },
  "f44314": {
   "value": "1437000",
   "decimals": -3,
   "dimensions": {
    "concept": "ifrs-full:OtherNoncurrentPayables",
    "entity": "scheme:213800PDI9G7OUKLPV84",
    "period": "2021-01-01T00:00:00",
    "unit": "iso4217:USD"
   }
  },
  "f44321": {
   "value": "53033000",
   "decimals": -3,
   "dimensions": {
    "concept": "ifrs-full:NoncurrentLiabilities",
    "entity": "scheme:213800PDI9G7OUKLPV84",
    "period": "2022-01-01T00:00:00",
    "unit": "iso4217:USD"
   }
  },
  "f44325": {
   "value": "34189000",
   "decimals": -3,
   "dimensions": {
    "concept": "ifrs-full:NoncurrentLiabilities",
    "entity": "scheme:213800PDI9G7OUKLPV84",
    "period": "2021-01-01T00:00:00",
    "unit": "iso4217:USD"
   }
  },
  "f44337": {
   "value": "75759000",
   "decimals": -3,
   "dimensions": {
    "concept": "ifrs-full:TradeAndOtherCurrentPayables",
    "entity": "scheme:213800PDI9G7OUKLPV84",
    "period": "2022-01-01T00:00:00",
    "unit": "iso4217:USD"
   }
  },
  "f44341": {
   "value": "64488000",
   "decimals": -3,
   "dimensions": {
    "concept": "ifrs-full:TradeAndOtherCurrentPayables",
    "entity": "scheme:213800PDI9G7OUKLPV84",
    "period": "2021-01-01T00:00:00",
    "unit": "iso4217:USD"
   }
  },
  "f44351": {
   "value": "253000",
   "decimals": -3,
   "dimensions": {
    "concept": "ifrs-full:CurrentTaxLiabilitiesCurrent",
    "entity": "scheme:213800PDI9G7OUKLPV84",
    "period": "2022-01-01T00:00:00",
    "unit": "iso4217:USD"
   }
  },
  "f44355": {
   "value": "267000",
   "decimals": -3,
   "dimensions": {
    "concept": "ifrs-full:CurrentTaxLiabilitiesCurrent",
    "entity": "scheme:213800PDI9G7OUKLPV84",
    "period": "2021-01-01T00:00:00",
    "unit": "iso4217:USD"
   }
  },
  "f44363": {
   "value": "4617000",
   "decimals": -3,
   "dimensions": {
    "concept": "ifrs-full:CurrentProvisions",
    "entity": "scheme:213800PDI9G7OUKLPV84",
    "period": "2022-01-01T00:00:00",
    "unit": "iso4217:USD"
   }
  },
  "f44370": {
   "value": "7480000",
   "decimals": -3,
   "dimensions": {
    "concept": "ifrs-full:CurrentProvisions",
    "entity": "scheme:213800PDI9G7OUKLPV84",
    "period": "2021-01-01T00:00:00",
    "unit": "iso4217:USD"
   }
  },
  "f44379": {
   "value": "80629000",
   "decimals": -3,
   "dimensions": {
    "concept": "ifrs-full:CurrentLiabilities",
    "entity": "scheme:213800PDI9G7OUKLPV84",
    "period": "2022-01-01T00:00:00",
    "unit": "iso4217:USD"
   }
  },
  "f44383": {
   "value": "72235000",
   "decimals": -3,
   "dimensions": {
    "concept": "ifrs-full:CurrentLiabilities",
    "entity": "scheme:213800PDI9G7OUKLPV84",
    "period": "2021-01-01T00:00:00",
    "unit": "iso4217:USD"
   }
  },
  "f44390": {
   "value": "133662000",
   "decimals": -3,
   "dimensions": {
    "concept": "ifrs-full:Liabilities",
    "entity": "scheme:213800PDI9G7OUKLPV84",
    "period": "2022-01-01T00:00:00",
    "unit": "iso4217:USD"
   }
  },
  "f44396": {
   "value": "106424000",
   "decimals": -3,
   "dimensions": {
    "concept": "ifrs-full:Liabilities",
    "entity": "scheme:213800PDI9G7OUKLPV84",
    "period": "2021-01-01T00:00:00",
    "unit": "iso4217:USD"
   }
  },
  "f44405": {
   "value": "1289758000",
   "decimals": -3,
   "dimensions": {
    "concept": "ifrs-full:NetAssetsLiabilities",
    "entity": "scheme:213800PDI9G7OUKLPV84",
    "period": "2022-01-01T00:00:00",
    "unit": "iso4217:USD"
   }
  },
  "f44411": {
   "value": "1289452000",
   "decimals": -3,
   "dimensions": {
    "concept": "ifrs-full:NetAssetsLiabilities",
    "entity": "scheme:213800PDI9G7OUKLPV84",
    "period": "2021-01-01T00:00:00",
    "unit": "iso4217:USD"
   }
  },
  "f44423": {
   "value": "669531000",
   "decimals": -3,
   "dimensions": {
    "concept": "ifrs-full:IssuedCapital",
    "entity": "scheme:213800PDI9G7OUKLPV84",
    "period": "2022-01-01T00:00:00",
    "unit": "iso4217:USD"
   }
  },
  "f44427": {
   "value": "668807000",
   "decimals": -3,
   "dimensions": {
    "concept": "ifrs-full:IssuedCapital",
    "entity": "scheme:213800PDI9G7OUKLPV84",
    "period": "2021-01-01T00:00:00",
    "unit": "iso4217:USD"
   }
  },
  "f44434": {
   "value": "4975000",
   "decimals": -3,
   "dimensions": {
    "concept": "ifrs-full:ReserveOfSharebasedPayments",
    "entity": "scheme:213800PDI9G7OUKLPV84",
    "period": "2022-01-01T00:00:00",
    "unit": "iso4217:USD"
   }
  },
  "f44438": {
   "value": "3343000",
   "decimals": -3,
   "dimensions": {
    "concept": "ifrs-full:ReserveOfSharebasedPayments",
    "entity": "scheme:213800PDI9G7OUKLPV84",
    "period": "2021-01-01T00:00:00",
    "unit": "iso4217:USD"
   }
  },
  "f44444": {
   "value": "655508000",
   "decimals": -3,
   "dimensions": {
    "concept": "ifrs-full:RetainedEarnings",
    "entity": "scheme:213800PDI9G7OUKLPV84",
    "period": "2022-01-01T00:00:00",
    "unit": "iso4217:USD"
   }
  },
  "f44448": {
   "value": "634498000",
   "decimals": -3,
   "dimensions": {
    "concept": "ifrs-full:RetainedEarnings",
    "entity": "scheme:213800PDI9G7OUKLPV84",
    "period": "2021-01-01T00:00:00",
    "unit": "iso4217:USD"
   }
  },
  "f44457": {
   "value": "1330014000",
   "decimals": -3,
   "dimensions": {
    "concept": "ifrs-full:EquityAttributableToOwnersOfParent",
    "entity": "scheme:213800PDI9G7OUKLPV84",
    "period": "2022-01-01T00:00:00",
    "unit": "iso4217:USD"
   }
  },
  "f44466": {
   "value": "1306648000",
   "decimals": -3,
   "dimensions": {
    "concept": "ifrs-full:EquityAttributableToOwnersOfParent",
    "entity": "scheme:213800PDI9G7OUKLPV84",
    "period": "2021-01-01T00:00:00",
    "unit": "iso4217:USD"
   }
  },
  "f44474": {
   "value": "-40256000",
   "decimals": -3,
   "dimensions": {
    "concept": "ifrs-full:NoncontrollingInterests",
    "entity": "scheme:213800PDI9G7OUKLPV84",
    "period": "2022-01-01T00:00:00",
    "unit": "iso4217:USD"
   }
  },
  "f44478": {
   "value": "-17196000",
   "decimals": -3,
   "dimensions": {
    "concept": "ifrs-full:NoncontrollingInterests",
    "entity": "scheme:213800PDI9G7OUKLPV84",
    "period": "2021-01-01T00:00:00",
    "unit": "iso4217:USD"
   }
  },
  "f44484": {
   "value": "1289758000",
   "decimals": -3,
   "dimensions": {
    "concept": "ifrs-full:Equity",
    "entity": "scheme:213800PDI9G7OUKLPV84",
    "period": "2022-01-01T00:00:00",
    "unit": "iso4217:USD"
   }
  },
  "f44490": {
   "value": "1289452000",
   "decimals": -3,
   "dimensions": {
    "concept": "ifrs-full:Equity",
    "entity": "scheme:213800PDI9G7OUKLPV84",
    "period": "2021-01-01T00:00:00",
    "unit": "iso4217:USD"
   }
  },
  "f44528": {
   "value": "733306000",
   "decimals": -3,
   "dimensions": {
    "concept": "ifrs-full:Revenue",
    "entity": "scheme:213800PDI9G7OUKLPV84",
    "period": "2021-01-01T00:00:00/2022-01-01T00:00:00",
    "unit": "iso4217:USD"
   }
  },
  "f44532": {
   "value": "828737000",
   "decimals": -3,
   "dimensions": {
    "concept": "ifrs-full:Revenue",
    "entity": "scheme:213800PDI9G7OUKLPV84",
    "period": "2020-01-01T00:00:00/2021-01-01T00:00:00",
    "unit": "iso4217:USD"
   }
  },
  "f44540": {
   "value": "487376000",
   "decimals": -3,
   "dimensions": {
    "concept": "ifrs-full:CostOfSales",
    "entity": "scheme:213800PDI9G7OUKLPV84",
    "period": "2021-01-01T00:00:00/2022-01-01T00:00:00",
    "unit": "iso4217:USD"
   }
  },
  "f44545": {
   "value": "449441000",
   "decimals": -3,
   "dimensions": {
    "concept": "ifrs-full:CostOfSales",
    "entity": "scheme:213800PDI9G7OUKLPV84",
    "period": "2020-01-01T00:00:00/2021-01-01T00:00:00",
    "unit": "iso4217:USD"
   }
  },
  "f44550": {
   "value": "245930000",
   "decimals": -3,
   "dimensions": {
    "concept": "ifrs-full:GrossProfit",
    "entity": "scheme:213800PDI9G7OUKLPV84",
    "period": "2021-01-01T00:00:00/2022-01-01T00:00:00",
    "unit": "iso4217:USD"
   }
  },
  "f44555": {
   "value": "379296000",
   "decimals": -3,
   "dimensions": {
    "concept": "ifrs-full:GrossProfit",
    "entity": "scheme:213800PDI9G7OUKLPV84",
    "period": "2020-01-01T00:00:00/2021-01-01T00:00:00",
    "unit": "iso4217:USD"
   }
  },
  "f44563": {
   "value": "13879000",
   "decimals": -3,
   "dimensions": {
    "concept": "ifrs-full:ExpenseArisingFromExplorationForAndEvaluationOfMineralResources",
    "entity": "scheme:213800PDI9G7OUKLPV84",
    "period": "2021-01-01T00:00:00/2022-01-01T00:00:00",
    "unit": "iso4217:USD"
   }
  },
  "f44571": {
   "value": "17391000",
   "decimals": -3,
   "dimensions": {
    "concept": "ifrs-full:ExpenseArisingFromExplorationForAndEvaluationOfMineralResources",
    "entity": "scheme:213800PDI9G7OUKLPV84",
    "period": "2020-01-01T00:00:00/2021-01-01T00:00:00",
    "unit": "iso4217:USD"
   }
  },
  "f44584": {
   "value": "49100000",
   "decimals": -3,
   "dimensions": {
    "concept": "ifrs-full:MiscellaneousOtherOperatingExpense",
    "entity": "scheme:213800PDI9G7OUKLPV84",
    "period": "2021-01-01T00:00:00/2022-01-01T00:00:00",
    "unit": "iso4217:USD"
   }
  },
  "f44593": {
   "value": "56392000",
   "decimals": -3,
   "dimensions": {
    "concept": "ifrs-full:MiscellaneousOtherOperatingExpense",
    "entity": "scheme:213800PDI9G7OUKLPV84",
    "period": "2020-01-01T00:00:00/2021-01-01T00:00:00",
    "unit": "iso4217:USD"
   }
  },
  "f44600": {
   "value": "5708000",
   "decimals": -3,
   "dimensions": {
    "concept": "ifrs-full:OtherIncome",
    "entity": "scheme:213800PDI9G7OUKLPV84",
    "period": "2021-01-01T00:00:00/2022-01-01T00:00:00",
    "unit": "iso4217:USD"
   }
  },
  "f44606": {
   "value": "6972000",
   "decimals": -3,
   "dimensions": {
    "concept": "ifrs-full:OtherIncome",
    "entity": "scheme:213800PDI9G7OUKLPV84",
    "period": "2020-01-01T00:00:00/2021-01-01T00:00:00",
    "unit": "iso4217:USD"
   }
  },
  "f44616": {
   "value": "960000",
   "decimals": -3,
   "dimensions": {
    "concept": "ifrs-full:GainsLossesOnFinancialAssetsAtFairValueThroughProfitOrLoss",
    "entity": "scheme:213800PDI9G7OUKLPV84",
    "period": "2020-01-01T00:00:00/2021-01-01T00:00:00",
    "unit": "iso4217:USD"
   }
  },
  "f44623": {
   "value": "196000",
   "decimals": -3,
   "dimensions": {
    "concept": "ifrs-full:FinanceIncome",
    "entity": "scheme:213800PDI9G7OUKLPV84",
    "period": "2021-01-01T00:00:00/2022-01-01T00:00:00",
    "unit": "iso4217:USD"
   }
  },
  "f44627": {
   "value": "1554000",
   "decimals": -3,
   "dimensions": {
    "concept": "ifrs-full:FinanceIncome",
    "entity": "scheme:213800PDI9G7OUKLPV84",
    "period": "2020-01-01T00:00:00/2021-01-01T00:00:00",
    "unit": "iso4217:USD"
   }
  },
  "f44637": {
   "value": "35208000",
   "decimals": -3,
   "dimensions": {
    "concept": "cey:ImpairmentOfExplorationAndEvaluationAsset",
    "entity": "scheme:213800PDI9G7OUKLPV84",
    "period": "2021-01-01T00:00:00/2022-01-01T00:00:00",
    "unit": "iso4217:USD"
   }
  },
  "f44645": {
   "value": "153647000",
   "decimals": -3,
   "dimensions": {
    "concept": "ifrs-full:ProfitLossBeforeTax",
    "entity": "scheme:213800PDI9G7OUKLPV84",
    "period": "2021-01-01T00:00:00/2022-01-01T00:00:00",
    "unit": "iso4217:USD"
   }
  },
  "f44649": {
   "value": "314999000",
   "decimals": -3,
   "dimensions": {
    "concept": "ifrs-full:ProfitLossBeforeTax",
    "entity": "scheme:213800PDI9G7OUKLPV84",
    "period": "2020-01-01T00:00:00/2021-01-01T00:00:00",
    "unit": "iso4217:USD"
   }
  },
  "f44658": {
   "value": "-20000",
   "decimals": -3,
   "dimensions": {
    "concept": "ifrs-full:IncomeTaxExpenseContinuingOperations",
    "entity": "scheme:213800PDI9G7OUKLPV84",
    "period": "2021-01-01T00:00:00/2022-01-01T00:00:00",
    "unit": "iso4217:USD"
   }
  },
  "f44662": {
   "value": "50000",
   "decimals": -3,
   "dimensions": {
    "concept": "ifrs-full:IncomeTaxExpenseContinuingOperations",
    "entity": "scheme:213800PDI9G7OUKLPV84",
    "period": "2020-01-01T00:00:00/2021-01-01T00:00:00",
    "unit": "iso4217:USD"
   }
  },
  "f44668": {
   "value": "153667000",
   "decimals": -3,
   "dimensions": {
    "concept": "ifrs-full:ProfitLoss",
    "entity": "scheme:213800PDI9G7OUKLPV84",
    "period": "2021-01-01T00:00:00/2022-01-01T00:00:00",
    "unit": "iso4217:USD"
   }
  },
  "f44676": {
   "value": "314949000",
   "decimals": -3,
   "dimensions": {
    "concept": "ifrs-full:ProfitLoss",
    "entity": "scheme:213800PDI9G7OUKLPV84",
    "period": "2020-01-01T00:00:00/2021-01-01T00:00:00",
    "unit": "iso4217:USD"
   }
  },
  "f44683": {
   "value": "101527000",
   "decimals": -3,
   "dimensions": {
    "concept": "ifrs-full:ProfitLossAttributableToOwnersOfParent",
    "entity": "scheme:213800PDI9G7OUKLPV84",
    "period": "2021-01-01T00:00:00/2022-01-01T00:00:00",
    "unit": "iso4217:USD"
   }
  },
  "f44689": {
   "value": "155979000",
   "decimals": -3,
   "dimensions": {
    "concept": "ifrs-full:ProfitLossAttributableToOwnersOfParent",
    "entity": "scheme:213800PDI9G7OUKLPV84",
    "period": "2020-01-01T00:00:00/2021-01-01T00:00:00",
    "unit": "iso4217:USD"
   }
  },
  "f44699": {
   "value": "52140000",
   "decimals": -3,
   "dimensions": {
    "concept": "ifrs-full:ProfitLossAttributableToNoncontrollingInterests",
    "entity": "scheme:213800PDI9G7OUKLPV84",
    "period": "2021-01-01T00:00:00/2022-01-01T00:00:00",
    "unit": "iso4217:USD"
   }
  },
  "f44706": {
   "value": "158970000",
   "decimals": -3,
   "dimensions": {
    "concept": "ifrs-full:ProfitLossAttributableToNoncontrollingInterests",
    "entity": "scheme:213800PDI9G7OUKLPV84",
    "period": "2020-01-01T00:00:00/2021-01-01T00:00:00",
    "unit": "iso4217:USD"
   }
  },
  "f44715": {
   "value": "153667000",
   "decimals": -3,
   "dimensions": {
    "concept": "ifrs-full:ComprehensiveIncome",
    "entity": "scheme:213800PDI9G7OUKLPV84",
    "period": "2021-01-01T00:00:00/2022-01-01T00:00:00",
    "unit": "iso4217:USD"
   }
  },
  "f44724": {
   "value": "314949000",
   "decimals": -3,
   "dimensions": {
    "concept": "ifrs-full:ComprehensiveIncome",
    "entity": "scheme:213800PDI9G7OUKLPV84",
    "period": "2020-01-01T00:00:00/2021-01-01T00:00:00",
    "unit": "iso4217:USD"
   }
  },
  "f44732": {
   "value": "101527000",
   "decimals": -3,
   "dimensions": {
    "concept": "ifrs-full:ComprehensiveIncomeAttributableToOwnersOfParent",
    "entity": "scheme:213800PDI9G7OUKLPV84",
    "period": "2021-01-01T00:00:00/2022-01-01T00:00:00",
    "unit": "iso4217:USD"
   }
  },
  "f44738": {
   "value": "155979000",
   "decimals": -3,
   "dimensions": {
    "concept": "ifrs-full:ComprehensiveIncomeAttributableToOwnersOfParent",
    "entity": "scheme:213800PDI9G7OUKLPV84",
    "period": "2020-01-01T00:00:00/2021-01-01T00:00:00",
    "unit": "iso4217:USD"
   }
  },
  "f44747": {
   "value": "52140000",
   "decimals": -3,
   "dimensions": {
    "concept": "ifrs-full:ComprehensiveIncomeAttributableToNoncontrollingInterests",
    "entity": "scheme:213800PDI9G7OUKLPV84",
    "period": "2021-01-01T00:00:00/2022-01-01T00:00:00",
    "unit": "iso4217:USD"
   }
  },
  "f44751": {
   "value": "158970000",
   "decimals": -3,
   "dimensions": {
    "concept": "ifrs-full:ComprehensiveIncomeAttributableToNoncontrollingInterests",
    "entity": "scheme:213800PDI9G7OUKLPV84",
    "period": "2020-01-01T00:00:00/2021-01-01T00:00:00",
    "unit": "iso4217:USD"
   }
  },
  "f44762": {
   "value": "0.08811",
   "dimensions": {
    "concept": "ifrs-full:BasicEarningsLossPerShare",
    "entity": "scheme:213800PDI9G7OUKLPV84",
    "period": "2021-01-01T00:00:00/2022-01-01T00:00:00",
    "unit": "iso4217:USD/xbrli:shares"
   }
  },
  "f44769": {
   "value": "0.13531",
   "dimensions": {
    "concept": "ifrs-full:BasicEarningsLossPerShare",
    "entity": "scheme:213800PDI9G7OUKLPV84",
    "period": "2020-01-01T00:00:00/2021-01-01T00:00:00",
    "unit": "iso4217:USD/xbrli:shares"
   }
  },
  "f44778": {
   "value": "0.08738",
   "dimensions": {
    "concept": "ifrs-full:DilutedEarningsLossPerShare",
    "entity": "scheme:213800PDI9G7OUKLPV84",
    "period": "2021-01-01T00:00:00/2022-01-01T00:00:00",
    "unit": "iso4217:USD/xbrli:shares"
   }
  },
  "f44784": {
   "value": "0.13453",
   "dimensions": {
    "concept": "ifrs-full:DilutedEarningsLossPerShare",
    "entity": "scheme:213800PDI9G7OUKLPV84",
    "period": "2020-01-01T00:00:00/2021-01-01T00:00:00",
    "unit": "iso4217:USD/xbrli:shares"
   }
  },
  "f44835": {
   "value": "309873000",
   "decimals": -3,
   "dimensions": {
    "concept": "ifrs-full:CashFlowsFromUsedInOperations",
    "entity": "scheme:213800PDI9G7OUKLPV84",
    "period": "2021-01-01T00:00:00/2022-01-01T00:00:00",
    "unit": "iso4217:USD"
   }
  },
  "f44840": {
   "value": "453315000",
   "decimals": -3,
   "dimensions": {
    "concept": "ifrs-full:CashFlowsFromUsedInOperations",
    "entity": "scheme:213800PDI9G7OUKLPV84",
    "period": "2020-01-01T00:00:00/2021-01-01T00:00:00",
    "unit": "iso4217:USD"
   }
  },
  "f44847": {
   "value": "-5000",
   "decimals": -3,
   "dimensions": {
    "concept": "ifrs-full:IncomeTaxesPaidRefundClassifiedAsOperatingActivities",
    "entity": "scheme:213800PDI9G7OUKLPV84",
    "period": "2021-01-01T00:00:00/2022-01-01T00:00:00",
    "unit": "iso4217:USD"
   }
  },
  "f44851": {
   "value": "10000",
   "decimals": -3,
   "dimensions": {
    "concept": "ifrs-full:IncomeTaxesPaidRefundClassifiedAsOperatingActivities",
    "entity": "scheme:213800PDI9G7OUKLPV84",
    "period": "2020-01-01T00:00:00/2021-01-01T00:00:00",
    "unit": "iso4217:USD"
   }
  },
  "f44857": {
   "value": "309878000",
   "decimals": -3,
   "dimensions": {
    "concept": "ifrs-full:CashFlowsFromUsedInOperatingActivities",
    "entity": "scheme:213800PDI9G7OUKLPV84",
    "period": "2021-01-01T00:00:00/2022-01-01T00:00:00",
    "unit": "iso4217:USD"
   }
  },
  "f44862": {
   "value": "453305000",
   "decimals": -3,
   "dimensions": {
    "concept": "ifrs-full:CashFlowsFromUsedInOperatingActivities",
    "entity": "scheme:213800PDI9G7OUKLPV84",
    "period": "2020-01-01T00:00:00/2021-01-01T00:00:00",
    "unit": "iso4217:USD"
   }
  },
  "f44871": {
   "value": "7414000",
   "decimals": -3,
   "dimensions": {
    "concept": "ifrs-full:ProceedsFromDisposalOrMaturityOfAvailableforsaleFinancialAssets",
    "entity": "scheme:213800PDI9G7OUKLPV84",
    "period": "2020-01-01T00:00:00/2021-01-01T00:00:00",
    "unit": "iso4217:USD"
   }
  },
  "f44880": {
   "value": "224929000",
   "decimals": -3,
   "dimensions": {
    "concept": "ifrs-full:PurchaseOfPropertyPlantAndEquipmentClassifiedAsInvestingActivities",
    "entity": "scheme:213800PDI9G7OUKLPV84",
    "period": "2021-01-01T00:00:00/2022-01-01T00:00:00",
    "unit": "iso4217:USD"
   }
  },
  "f44883": {
   "value": "127099000",
   "decimals": -3,
   "dimensions": {
    "concept": "ifrs-full:PurchaseOfPropertyPlantAndEquipmentClassifiedAsInvestingActivities",
    "entity": "scheme:213800PDI9G7OUKLPV84",
    "period": "2020-01-01T00:00:00/2021-01-01T00:00:00",
    "unit": "iso4217:USD"
   }
  },
  "f44895": {
   "value": "-15943000",
   "decimals": -3,
   "dimensions": {
    "concept": "cey:BrownfieldExplorationAndEvaluationExpenditure",
    "entity": "scheme:213800PDI9G7OUKLPV84",
    "period": "2021-01-01T00:00:00/2022-01-01T00:00:00",
    "unit": "iso4217:USD"
   }
  },
  "f44901": {
   "value": "-11717000",
   "decimals": -3,
   "dimensions": {
    "concept": "cey:BrownfieldExplorationAndEvaluationExpenditure",
    "entity": "scheme:213800PDI9G7OUKLPV84",
    "period": "2020-01-01T00:00:00/2021-01-01T00:00:00",
    "unit": "iso4217:USD"
   }
  },
  "f44911": {
   "value": "-196000",
   "decimals": -3,
   "dimensions": {
    "concept": "cey:FinanceIncomeClassifiedAsInvestingActivities",
    "entity": "scheme:213800PDI9G7OUKLPV84",
    "period": "2021-01-01T00:00:00/2022-01-01T00:00:00",
    "unit": "iso4217:USD"
   }
  },
  "f44916": {
   "value": "-1554000",
   "decimals": -3,
   "dimensions": {
    "concept": "cey:FinanceIncomeClassifiedAsInvestingActivities",
    "entity": "scheme:213800PDI9G7OUKLPV84",
    "period": "2020-01-01T00:00:00/2021-01-01T00:00:00",
    "unit": "iso4217:USD"
   }
  },
  "f44923": {
   "value": "-240676000",
   "decimals": -3,
   "dimensions": {
    "concept": "ifrs-full:CashFlowsFromUsedInInvestingActivities",
    "entity": "scheme:213800PDI9G7OUKLPV84",
    "period": "2021-01-01T00:00:00/2022-01-01T00:00:00",
    "unit": "iso4217:USD"
   }
  },
  "f44928": {
   "value": "-129848000",
   "decimals": -3,
   "dimensions": {
    "concept": "ifrs-full:CashFlowsFromUsedInInvestingActivities",
    "entity": "scheme:213800PDI9G7OUKLPV84",
    "period": "2020-01-01T00:00:00/2021-01-01T00:00:00",
    "unit": "iso4217:USD"
   }
  },
  "f44936": {
   "value": "1391000",
   "decimals": -3,
   "dimensions": {
    "concept": "ifrs-full:PaymentsToAcquireOrRedeemEntitysShares",
    "entity": "scheme:213800PDI9G7OUKLPV84",
    "period": "2021-01-01T00:00:00/2022-01-01T00:00:00",
    "unit": "iso4217:USD"
   }
  },
  "f44943": {
   "value": "3298000",
   "decimals": -3,
   "dimensions": {
    "concept": "ifrs-full:PaymentsToAcquireOrRedeemEntitysShares",
    "entity": "scheme:213800PDI9G7OUKLPV84",
    "period": "2020-01-01T00:00:00/2021-01-01T00:00:00",
    "unit": "iso4217:USD"
   }
  },
  "f44951": {
   "value": "75200000",
   "decimals": -3,
   "dimensions": {
    "concept": "ifrs-full:DividendsPaidToNoncontrollingInterestsClassifiedAsFinancingActivities",
    "entity": "scheme:213800PDI9G7OUKLPV84",
    "period": "2021-01-01T00:00:00/2022-01-01T00:00:00",
    "unit": "iso4217:USD"
   }
  },
  "f44956": {
   "value": "174275000",
   "decimals": -3,
   "dimensions": {
    "concept": "ifrs-full:DividendsPaidToNoncontrollingInterestsClassifiedAsFinancingActivities",
    "entity": "scheme:213800PDI9G7OUKLPV84",
    "period": "2020-01-01T00:00:00/2021-01-01T00:00:00",
    "unit": "iso4217:USD"
   }
  },
  "f44967": {
   "value": "80517000",
   "decimals": -3,
   "dimensions": {
    "concept": "ifrs-full:DividendsPaidToEquityHoldersOfParentClassifiedAsFinancingActivities",
    "entity": "scheme:213800PDI9G7OUKLPV84",
    "period": "2021-01-01T00:00:00/2022-01-01T00:00:00",
    "unit": "iso4217:USD"
   }
  },
  "f44975": {
   "value": "138725000",
   "decimals": -3,
   "dimensions": {
    "concept": "ifrs-full:DividendsPaidToEquityHoldersOfParentClassifiedAsFinancingActivities",
    "entity": "scheme:213800PDI9G7OUKLPV84",
    "period": "2020-01-01T00:00:00/2021-01-01T00:00:00",
    "unit": "iso4217:USD"
   }
  },
  "f44980": {
   "value": "-157108000",
   "decimals": -3,
   "dimensions": {
    "concept": "ifrs-full:CashFlowsFromUsedInFinancingActivities",
    "entity": "scheme:213800PDI9G7OUKLPV84",
    "period": "2021-01-01T00:00:00/2022-01-01T00:00:00",
    "unit": "iso4217:USD"
   }
  },
  "f44987": {
   "value": "-316298000",
   "decimals": -3,
   "dimensions": {
    "concept": "ifrs-full:CashFlowsFromUsedInFinancingActivities",
    "entity": "scheme:213800PDI9G7OUKLPV84",
    "period": "2020-01-01T00:00:00/2021-01-01T00:00:00",
    "unit": "iso4217:USD"
   }
  },
  "f44993": {
   "value": "-87906000",
   "decimals": -3,
   "dimensions": {
    "concept": "ifrs-full:IncreaseDecreaseInCashAndCashEquivalents",
    "entity": "scheme:213800PDI9G7OUKLPV84",
    "period": "2021-01-01T00:00:00/2022-01-01T00:00:00",
    "unit": "iso4217:USD"
   }
  },
  "f45000": {
   "value": "7159000",
   "decimals": -3,
   "dimensions": {
    "concept": "ifrs-full:IncreaseDecreaseInCashAndCashEquivalents",
    "entity": "scheme:213800PDI9G7OUKLPV84",
    "period": "2020-01-01T00:00:00/2021-01-01T00:00:00",
    "unit": "iso4217:USD"
   }
  },
  "f45007": {
   "value": "291281000",
   "decimals": -3,
   "dimensions": {
    "concept": "ifrs-full:CashAndCashEquivalents",
    "entity": "scheme:213800PDI9G7OUKLPV84",
    "period": "2021-01-01T00:00:00",
    "unit": "iso4217:USD"
   }
  },
  "f45015": {
   "value": "278229000",
   "decimals": -3,
   "dimensions": {
    "concept": "ifrs-full:CashAndCashEquivalents",
    "entity": "scheme:213800PDI9G7OUKLPV84",
    "period": "2020-01-01T00:00:00",
    "unit": "iso4217:USD"
   }
  },
  "f45021": {
   "value": "4446000",
   "decimals": -3,
   "dimensions": {
    "concept": "ifrs-full:EffectOfExchangeRateChangesOnCashAndCashEquivalents",
    "entity": "scheme:213800PDI9G7OUKLPV84",
    "period": "2021-01-01T00:00:00/2022-01-01T00:00:00",
    "unit": "iso4217:USD"
   }
  },
  "f45025": {
   "value": "5893000",
   "decimals": -3,
   "dimensions": {
    "concept": "ifrs-full:EffectOfExchangeRateChangesOnCashAndCashEquivalents",
    "entity": "scheme:213800PDI9G7OUKLPV84",
    "period": "2020-01-01T00:00:00/2021-01-01T00:00:00",
    "unit": "iso4217:USD"
   }
  },
  "f45032": {
   "value": "207821000",
   "decimals": -3,
   "dimensions": {
    "concept": "ifrs-full:CashAndCashEquivalents",
    "entity": "scheme:213800PDI9G7OUKLPV84",
    "period": "2022-01-01T00:00:00",
    "unit": "iso4217:USD"
   }
  },
  "f45041": {
   "value": "291281000",
   "decimals": -3,
   "dimensions": {
    "concept": "ifrs-full:CashAndCashEquivalents",
    "entity": "scheme:213800PDI9G7OUKLPV84",
    "period": "2021-01-01T00:00:00",
    "unit": "iso4217:USD"
   }
  },
  "f45069": {
   "value": "668807000",
   "decimals": -3,
   "dimensions": {
    "concept": "ifrs-full:Equity",
    "entity": "scheme:213800PDI9G7OUKLPV84",
    "period": "2021-01-01T00:00:00",
    "ifrs-full:ComponentsOfEquityAxis": "ifrs-full:IssuedCapitalMember",
    "unit": "iso4217:USD"
   }
  },
  "f45074": {
   "value": "3343000",
   "decimals": -3,
   "dimensions": {
    "concept": "ifrs-full:Equity",
    "entity": "scheme:213800PDI9G7OUKLPV84",
    "period": "2021-01-01T00:00:00",
    "ifrs-full:ComponentsOfEquityAxis": "ifrs-full:ReserveOfSharebasedPaymentsMember",
    "unit": "iso4217:USD"
   }
  },
  "f45080": {
   "value": "634498000",
   "decimals": -3,
   "dimensions": {
    "concept": "ifrs-full:Equity",
    "entity": "scheme:213800PDI9G7OUKLPV84",
    "period": "2021-01-01T00:00:00",
    "ifrs-full:ComponentsOfEquityAxis": "ifrs-full:RetainedEarningsMember",
    "unit": "iso4217:USD"
   }
  },
  "f45084": {
   "value": "1306648000",
   "decimals": -3,
   "dimensions": {
    "concept": "ifrs-full:Equity",
    "entity": "scheme:213800PDI9G7OUKLPV84",
    "period": "2021-01-01T00:00:00",
    "ifrs-full:ComponentsOfEquityAxis": "ifrs-full:EquityAttributableToOwnersOfParentMember",
    "unit": "iso4217:USD"
   }
  },
  "f45091": {
   "value": "-17196000",
   "decimals": -3,
   "dimensions": {
    "concept": "ifrs-full:Equity",
    "entity": "scheme:213800PDI9G7OUKLPV84",
    "period": "2021-01-01T00:00:00",
    "ifrs-full:ComponentsOfEquityAxis": "ifrs-full:NoncontrollingInterestsMember",
    "unit": "iso4217:USD"
   }
  },
  "f45100": {
   "value": "1289452000",
   "decimals": -3,
   "dimensions": {
    "concept": "ifrs-full:Equity",
    "entity": "scheme:213800PDI9G7OUKLPV84",
    "period": "2021-01-01T00:00:00",
    "unit": "iso4217:USD"
   }
  },
  "f45109": {
   "value": "101527000",
   "decimals": -3,
   "dimensions": {
    "concept": "ifrs-full:ProfitLoss",
    "entity": "scheme:213800PDI9G7OUKLPV84",
    "period": "2021-01-01T00:00:00/2022-01-01T00:00:00",
    "ifrs-full:ComponentsOfEquityAxis": "ifrs-full:RetainedEarningsMember",
    "unit": "iso4217:USD"
   }
  },
  "f45114": {
   "value": "101527000",
   "decimals": -3,
   "dimensions": {
    "concept": "ifrs-full:ProfitLoss",
    "entity": "scheme:213800PDI9G7OUKLPV84",
    "period": "2021-01-01T00:00:00/2022-01-01T00:00:00",
    "ifrs-full:ComponentsOfEquityAxis": "ifrs-full:EquityAttributableToOwnersOfParentMember",
    "unit": "iso4217:USD"
   }
  },
  "f45120": {
   "value": "52140000",
   "decimals": -3,
   "dimensions": {
    "concept": "ifrs-full:ProfitLoss",
    "entity": "scheme:213800PDI9G7OUKLPV84",
    "period": "2021-01-01T00:00:00/2022-01-01T00:00:00",
    "ifrs-full:ComponentsOfEquityAxis": "ifrs-full:NoncontrollingInterestsMember",
    "unit": "iso4217:USD"
   }
  },
  "f45127": {
   "value": "153667000",
   "decimals": -3,
   "dimensions": {
    "concept": "ifrs-full:ProfitLoss",
    "entity": "scheme:213800PDI9G7OUKLPV84",
    "period": "2021-01-01T00:00:00/2022-01-01T00:00:00",
    "unit": "iso4217:USD"
   }
  },
  "f45141": {
   "value": "101527000",
   "decimals": -3,
   "dimensions": {
    "concept": "ifrs-full:ComprehensiveIncome",
    "entity": "scheme:213800PDI9G7OUKLPV84",
    "period": "2021-01-01T00:00:00/2022-01-01T00:00:00",
    "ifrs-full:ComponentsOfEquityAxis": "ifrs-full:RetainedEarningsMember",
    "unit": "iso4217:USD"
   }
  },
  "f45146": {
   "value": "101527000",
   "decimals": -3,
   "dimensions": {
    "concept": "ifrs-full:ComprehensiveIncome",
    "entity": "scheme:213800PDI9G7OUKLPV84",
    "period": "2021-01-01T00:00:00/2022-01-01T00:00:00",
    "ifrs-full:ComponentsOfEquityAxis": "ifrs-full:EquityAttributableToOwnersOfParentMember",
    "unit": "iso4217:USD"
   }
  },
  "f45153": {
   "value": "52140000",
   "decimals": -3,
   "dimensions": {
    "concept": "ifrs-full:ComprehensiveIncome",
    "entity": "scheme:213800PDI9G7OUKLPV84",
    "period": "2021-01-01T00:00:00/2022-01-01T00:00:00",
    "ifrs-full:ComponentsOfEquityAxis": "ifrs-full:NoncontrollingInterestsMember",
    "unit": "iso4217:USD"
   }
  },
  "f45160": {
   "value": "153667000",
   "decimals": -3,
   "dimensions": {
    "concept": "ifrs-full:ComprehensiveIncome",
    "entity": "scheme:213800PDI9G7OUKLPV84",
    "period": "2021-01-01T00:00:00/2022-01-01T00:00:00",
    "unit": "iso4217:USD"
   }
  },
  "f45170": {
   "value": "1391000",
   "decimals": -3,
   "dimensions": {
    "concept": "ifrs-full:PurchaseOfTreasuryShares",
    "entity": "scheme:213800PDI9G7OUKLPV84",
    "period": "2021-01-01T00:00:00/2022-01-01T00:00:00",
    "ifrs-full:ComponentsOfEquityAxis": "ifrs-full:IssuedCapitalMember",
    "unit": "iso4217:USD"
   }
  },
  "f45179": {
   "value": "1391000",
   "decimals": -3,
   "dimensions": {
    "concept": "ifrs-full:PurchaseOfTreasuryShares",
    "entity": "scheme:213800PDI9G7OUKLPV84",
    "period": "2021-01-01T00:00:00/2022-01-01T00:00:00",
    "ifrs-full:ComponentsOfEquityAxis": "ifrs-full:EquityAttributableToOwnersOfParentMember",
    "unit": "iso4217:USD"
   }
  },
  "f45187": {
   "value": "1391000",
   "decimals": -3,
   "dimensions": {
    "concept": "ifrs-full:PurchaseOfTreasuryShares",
    "entity": "scheme:213800PDI9G7OUKLPV84",
    "period": "2021-01-01T00:00:00/2022-01-01T00:00:00",
    "unit": "iso4217:USD"
   }
  },
  "f45198": {
   "value": "3747000",
   "decimals": -3,
   "dimensions": {
    "concept": "ifrs-full:IncreaseDecreaseThroughSharebasedPaymentTransactions",
    "entity": "scheme:213800PDI9G7OUKLPV84",
    "period": "2021-01-01T00:00:00/2022-01-01T00:00:00",
    "ifrs-full:ComponentsOfEquityAxis": "ifrs-full:ReserveOfSharebasedPaymentsMember",
    "unit": "iso4217:USD"
   }
  },
  "f45203": {
   "value": "3747000",
   "decimals": -3,
   "dimensions": {
    "concept": "ifrs-full:IncreaseDecreaseThroughSharebasedPaymentTransactions",
    "entity": "scheme:213800PDI9G7OUKLPV84",
    "period": "2021-01-01T00:00:00/2022-01-01T00:00:00",
    "ifrs-full:ComponentsOfEquityAxis": "ifrs-full:EquityAttributableToOwnersOfParentMember",
    "unit": "iso4217:USD"
   }
  },
  "f45208": {
   "value": "3747000",
   "decimals": -3,
   "dimensions": {
    "concept": "ifrs-full:IncreaseDecreaseThroughSharebasedPaymentTransactions",
    "entity": "scheme:213800PDI9G7OUKLPV84",
    "period": "2021-01-01T00:00:00/2022-01-01T00:00:00",
    "unit": "iso4217:USD"
   }
  },
  "f45214": {
   "value": "2115000",
   "decimals": -3,
   "dimensions": {
    "concept": "cey:TransferOfShareBasedPayments",
    "entity": "scheme:213800PDI9G7OUKLPV84",
    "period": "2021-01-01T00:00:00/2022-01-01T00:00:00",
    "ifrs-full:ComponentsOfEquityAxis": "ifrs-full:IssuedCapitalMember",
    "unit": "iso4217:USD"
   }
  },
  "f45219": {
   "value": "-2115000",
   "decimals": -3,
   "dimensions": {
    "concept": "cey:TransferOfShareBasedPayments",
    "entity": "scheme:213800PDI9G7OUKLPV84",
    "period": "2021-01-01T00:00:00/2022-01-01T00:00:00",
    "ifrs-full:ComponentsOfEquityAxis": "ifrs-full:ReserveOfSharebasedPaymentsMember",
    "unit": "iso4217:USD"
   }
  },
  "f45240": {
   "value": "75200000",
   "decimals": -3,
   "dimensions": {
    "concept": "ifrs-full:DividendsRecognisedAsDistributionsToNoncontrollingInterests",
    "entity": "scheme:213800PDI9G7OUKLPV84",
    "period": "2021-01-01T00:00:00/2022-01-01T00:00:00",
    "ifrs-full:ComponentsOfEquityAxis": "ifrs-full:NoncontrollingInterestsMember",
    "unit": "iso4217:USD"
   }
  },
  "f45244": {
   "value": "75200000",
   "decimals": -3,
   "dimensions": {
    "concept": "ifrs-full:DividendsRecognisedAsDistributionsToNoncontrollingInterests",
    "entity": "scheme:213800PDI9G7OUKLPV84",
    "period": "2021-01-01T00:00:00/2022-01-01T00:00:00",
    "unit": "iso4217:USD"
   }
  },
  "f45253": {
   "value": "80517000",
   "decimals": -3,
   "dimensions": {
    "concept": "ifrs-full:DividendsRecognisedAsDistributionsToOwnersOfParent",
    "entity": "scheme:213800PDI9G7OUKLPV84",
    "period": "2021-01-01T00:00:00/2022-01-01T00:00:00",
    "ifrs-full:ComponentsOfEquityAxis": "ifrs-full:RetainedEarningsMember",
    "unit": "iso4217:USD"
   }
  },
  "f45261": {
   "value": "80517000",
   "decimals": -3,
   "dimensions": {
    "concept": "ifrs-full:DividendsRecognisedAsDistributionsToOwnersOfParent",
    "entity": "scheme:213800PDI9G7OUKLPV84",
    "period": "2021-01-01T00:00:00/2022-01-01T00:00:00",
    "ifrs-full:ComponentsOfEquityAxis": "ifrs-full:EquityAttributableToOwnersOfParentMember",
    "unit": "iso4217:USD"
   }
  },
  "f45271": {
   "value": "80517000",
   "decimals": -3,
   "dimensions": {
    "concept": "ifrs-full:DividendsRecognisedAsDistributionsToOwnersOfParent",
    "entity": "scheme:213800PDI9G7OUKLPV84",
    "period": "2021-01-01T00:00:00/2022-01-01T00:00:00",
    "unit": "iso4217:USD"
   }
  },
  "f45281": {
   "value": "669531000",
   "decimals": -3,
   "dimensions": {
    "concept": "ifrs-full:Equity",
    "entity": "scheme:213800PDI9G7OUKLPV84",
    "period": "2022-01-01T00:00:00",
    "ifrs-full:ComponentsOfEquityAxis": "ifrs-full:IssuedCapitalMember",
    "unit": "iso4217:USD"
   }
  },
  "f45285": {
   "value": "4975000",
   "decimals": -3,
   "dimensions": {
    "concept": "ifrs-full:Equity",
    "entity": "scheme:213800PDI9G7OUKLPV84",
    "period": "2022-01-01T00:00:00",
    "ifrs-full:ComponentsOfEquityAxis": "ifrs-full:ReserveOfSharebasedPaymentsMember",
    "unit": "iso4217:USD"
   }
  },
  "f45290": {
   "value": "655508000",
   "decimals": -3,
   "dimensions": {
    "concept": "ifrs-full:Equity",
    "entity": "scheme:213800PDI9G7OUKLPV84",
    "period": "2022-01-01T00:00:00",
    "ifrs-full:ComponentsOfEquityAxis": "ifrs-full:RetainedEarningsMember",
    "unit": "iso4217:USD"
   }
  },
  "f45294": {
   "value": "1330014000",
   "decimals": -3,
   "dimensions": {
    "concept": "ifrs-full:Equity",
    "entity": "scheme:213800PDI9G7OUKLPV84",
    "period": "2022-01-01T00:00:00",
    "ifrs-full:ComponentsOfEquityAxis": "ifrs-full:EquityAttributableToOwnersOfParentMember",
    "unit": "iso4217:USD"
   }
  },
  "f45300": {
   "value": "-40256000",
   "decimals": -3,
   "dimensions": {
    "concept": "ifrs-full:Equity",
    "entity": "scheme:213800PDI9G7OUKLPV84",
    "period": "2022-01-01T00:00:00",
    "ifrs-full:ComponentsOfEquityAxis": "ifrs-full:NoncontrollingInterestsMember",
    "unit": "iso4217:USD"
   }
  },
  "f45305": {
   "value": "1289758000",
   "decimals": -3,
   "dimensions": {
    "concept": "ifrs-full:Equity",
    "entity": "scheme:213800PDI9G7OUKLPV84",
    "period": "2022-01-01T00:00:00",
    "unit": "iso4217:USD"
   }
  },
  "f45332": {
   "value": "672105000",
   "decimals": -3,
   "dimensions": {
    "concept": "ifrs-full:Equity",
    "entity": "scheme:213800PDI9G7OUKLPV84",
    "period": "2020-01-01T00:00:00",
    "ifrs-full:ComponentsOfEquityAxis": "ifrs-full:IssuedCapitalMember",
    "unit": "iso4217:USD"
   }
  },
  "f45339": {
   "value": "4179000",
   "decimals": -3,
   "dimensions": {
    "concept": "ifrs-full:Equity",
    "entity": "scheme:213800PDI9G7OUKLPV84",
    "period": "2020-01-01T00:00:00",
    "ifrs-full:ComponentsOfEquityAxis": "ifrs-full:ReserveOfSharebasedPaymentsMember",
    "unit": "iso4217:USD"
   }
  },
  "f45345": {
   "value": "617244000",
   "decimals": -3,
   "dimensions": {
    "concept": "ifrs-full:Equity",
    "entity": "scheme:213800PDI9G7OUKLPV84",
    "period": "2020-01-01T00:00:00",
    "ifrs-full:ComponentsOfEquityAxis": "ifrs-full:RetainedEarningsMember",
    "unit": "iso4217:USD"
   }
  },
  "f45355": {
   "value": "1293528000",
   "decimals": -3,
   "dimensions": {
    "concept": "ifrs-full:Equity",
    "entity": "scheme:213800PDI9G7OUKLPV84",
    "period": "2020-01-01T00:00:00",
    "ifrs-full:ComponentsOfEquityAxis": "ifrs-full:EquityAttributableToOwnersOfParentMember",
    "unit": "iso4217:USD"
   }
  },
  "f45362": {
   "value": "-1891000",
   "decimals": -3,
   "dimensions": {
    "concept": "ifrs-full:Equity",
    "entity": "scheme:213800PDI9G7OUKLPV84",
    "period": "2020-01-01T00:00:00",
    "ifrs-full:ComponentsOfEquityAxis": "ifrs-full:NoncontrollingInterestsMember",
    "unit": "iso4217:USD"
   }
  },
  "f45368": {
   "value": "1291637000",
   "decimals": -3,
   "dimensions": {
    "concept": "ifrs-full:Equity",
    "entity": "scheme:213800PDI9G7OUKLPV84",
    "period": "2020-01-01T00:00:00",
    "unit": "iso4217:USD"
   }
  },
  "f45377": {
   "value": "155979000",
   "decimals": -3,
   "dimensions": {
    "concept": "ifrs-full:ProfitLoss",
    "entity": "scheme:213800PDI9G7OUKLPV84",
    "period": "2020-01-01T00:00:00/2021-01-01T00:00:00",
    "ifrs-full:ComponentsOfEquityAxis": "ifrs-full:RetainedEarningsMember",
    "unit": "iso4217:USD"
   }
  },
  "f45383": {
   "value": "155979000",
   "decimals": -3,
   "dimensions": {
    "concept": "ifrs-full:ProfitLoss",
    "entity": "scheme:213800PDI9G7OUKLPV84",
    "period": "2020-01-01T00:00:00/2021-01-01T00:00:00",
    "ifrs-full:ComponentsOfEquityAxis": "ifrs-full:EquityAttributableToOwnersOfParentMember",
    "unit": "iso4217:USD"
   }
  },
  "f45388": {
   "value": "158970000",
   "decimals": -3,
   "dimensions": {
    "concept": "ifrs-full:ProfitLoss",
    "entity": "scheme:213800PDI9G7OUKLPV84",
    "period": "2020-01-01T00:00:00/2021-01-01T00:00:00",
    "ifrs-full:ComponentsOfEquityAxis": "ifrs-full:NoncontrollingInterestsMember",
    "unit": "iso4217:USD"
   }
  },
  "f45394": {
   "value": "314949000",
   "decimals": -3,
   "dimensions": {
    "concept": "ifrs-full:ProfitLoss",
    "entity": "scheme:213800PDI9G7OUKLPV84",
    "period": "2020-01-01T00:00:00/2021-01-01T00:00:00",
    "unit": "iso4217:USD"
   }
  },
  "f45405": {
   "value": "155979000",
   "decimals": -3,
   "dimensions": {
    "concept": "ifrs-full:ComprehensiveIncome",
    "entity": "scheme:213800PDI9G7OUKLPV84",
    "period": "2020-01-01T00:00:00/2021-01-01T00:00:00",
    "ifrs-full:ComponentsOfEquityAxis": "ifrs-full:RetainedEarningsMember",
    "unit": "iso4217:USD"
   }
  },
  "f45410": {
   "value": "155979000",
   "decimals": -3,
   "dimensions": {
    "concept": "ifrs-full:ComprehensiveIncome",
    "entity": "scheme:213800PDI9G7OUKLPV84",
    "period": "2020-01-01T00:00:00/2021-01-01T00:00:00",
    "ifrs-full:ComponentsOfEquityAxis": "ifrs-full:EquityAttributableToOwnersOfParentMember",
    "unit": "iso4217:USD"
   }
  },
  "f45415": {
   "value": "158970000",
   "decimals": -3,
   "dimensions": {
    "concept": "ifrs-full:ComprehensiveIncome",
    "entity": "scheme:213800PDI9G7OUKLPV84",
    "period": "2020-01-01T00:00:00/2021-01-01T00:00:00",
    "ifrs-full:ComponentsOfEquityAxis": "ifrs-full:NoncontrollingInterestsMember",
    "unit": "iso4217:USD"
   }
  },
  "f45422": {
   "value": "314949000",
   "decimals": -3,
   "dimensions": {
    "concept": "ifrs-full:ComprehensiveIncome",
    "entity": "scheme:213800PDI9G7OUKLPV84",
    "period": "2020-01-01T00:00:00/2021-01-01T00:00:00",
    "unit": "iso4217:USD"
   }
  },
  "f45428": {
   "value": "3298000",
   "decimals": -3,
   "dimensions": {
    "concept": "ifrs-full:PurchaseOfTreasuryShares",
    "entity": "scheme:213800PDI9G7OUKLPV84",
    "period": "2020-01-01T00:00:00/2021-01-01T00:00:00",
    "ifrs-full:ComponentsOfEquityAxis": "ifrs-full:IssuedCapitalMember",
    "unit": "iso4217:USD"
   }
  },
  "f45436": {
   "value": "3298000",
   "decimals": -3,
   "dimensions": {
    "concept": "ifrs-full:PurchaseOfTreasuryShares",
    "entity": "scheme:213800PDI9G7OUKLPV84",
    "period": "2020-01-01T00:00:00/2021-01-01T00:00:00",
    "ifrs-full:ComponentsOfEquityAxis": "ifrs-full:EquityAttributableToOwnersOfParentMember",
    "unit": "iso4217:USD"
   }
  },
  "f45442": {
   "value": "3298000",
   "decimals": -3,
   "dimensions": {
    "concept": "ifrs-full:PurchaseOfTreasuryShares",
    "entity": "scheme:213800PDI9G7OUKLPV84",
    "period": "2020-01-01T00:00:00/2021-01-01T00:00:00",
    "unit": "iso4217:USD"
   }
  },
  "f45450": {
   "value": "-836000",
   "decimals": -3,
   "dimensions": {
    "concept": "cey:NetReversalOfShareBasedPayments",
    "entity": "scheme:213800PDI9G7OUKLPV84",
    "period": "2020-01-01T00:00:00/2021-01-01T00:00:00",
    "ifrs-full:ComponentsOfEquityAxis": "ifrs-full:ReserveOfSharebasedPaymentsMember",
    "unit": "iso4217:USD"
   }
  },
  "f45456": {
   "value": "-836000",
   "decimals": -3,
   "dimensions": {
    "concept": "cey:NetReversalOfShareBasedPayments",
    "entity": "scheme:213800PDI9G7OUKLPV84",
    "period": "2020-01-01T00:00:00/2021-01-01T00:00:00",
    "ifrs-full:ComponentsOfEquityAxis": "ifrs-full:EquityAttributableToOwnersOfParentMember",
    "unit": "iso4217:USD"
   }
  },
  "f45461": {
   "value": "-836000",
   "decimals": -3,
   "dimensions": {
    "concept": "cey:NetReversalOfShareBasedPayments",
    "entity": "scheme:213800PDI9G7OUKLPV84",
    "period": "2020-01-01T00:00:00/2021-01-01T00:00:00",
    "unit": "iso4217:USD"
   }
  },
  "f45475": {
   "value": "174275000",
   "decimals": -3,
   "dimensions": {
    "concept": "ifrs-full:DividendsRecognisedAsDistributionsToNoncontrollingInterests",
    "entity": "scheme:213800PDI9G7OUKLPV84",
    "period": "2020-01-01T00:00:00/2021-01-01T00:00:00",
    "ifrs-full:ComponentsOfEquityAxis": "ifrs-full:NoncontrollingInterestsMember",
    "unit": "iso4217:USD"
   }
  },
  "f45483": {
   "value": "174275000",
   "decimals": -3,
   "dimensions": {
    "concept": "ifrs-full:DividendsRecognisedAsDistributionsToNoncontrollingInterests",
    "entity": "scheme:213800PDI9G7OUKLPV84",
    "period": "2020-01-01T00:00:00/2021-01-01T00:00:00",
    "unit": "iso4217:USD"
   }
  },
  "f45495": {
   "value": "138725000",
   "decimals": -3,
   "dimensions": {
    "concept": "ifrs-full:DividendsRecognisedAsDistributionsToOwnersOfParent",
    "entity": "scheme:213800PDI9G7OUKLPV84",
    "period": "2020-01-01T00:00:00/2021-01-01T00:00:00",
    "ifrs-full:ComponentsOfEquityAxis": "ifrs-full:RetainedEarningsMember",
    "unit": "iso4217:USD"
   }
  },
  "f45500": {
   "value": "138725000",
   "decimals": -3,
   "dimensions": {
    "concept": "ifrs-full:DividendsRecognisedAsDistributionsToOwnersOfParent",
    "entity": "scheme:213800PDI9G7OUKLPV84",
    "period": "2020-01-01T00:00:00/2021-01-01T00:00:00",
    "ifrs-full:ComponentsOfEquityAxis": "ifrs-full:EquityAttributableToOwnersOfParentMember",
    "unit": "iso4217:USD"
   }
  },
  "f45507": {
   "value": "138725000",
   "decimals": -3,
   "dimensions": {
    "concept": "ifrs-full:DividendsRecognisedAsDistributionsToOwnersOfParent",
    "entity": "scheme:213800PDI9G7OUKLPV84",
    "period": "2020-01-01T00:00:00/2021-01-01T00:00:00",
    "unit": "iso4217:USD"
   }
  },
  "f45512": {
   "value": "668807000",
   "decimals": -3,
   "dimensions": {
    "concept": "ifrs-full:Equity",
    "entity": "scheme:213800PDI9G7OUKLPV84",
    "period": "2021-01-01T00:00:00",
    "ifrs-full:ComponentsOfEquityAxis": "ifrs-full:IssuedCapitalMember",
    "unit": "iso4217:USD"
   }
  },
  "f45516": {
   "value": "3343000",
   "decimals": -3,
   "dimensions": {
    "concept": "ifrs-full:Equity",
    "entity": "scheme:213800PDI9G7OUKLPV84",
    "period": "2021-01-01T00:00:00",
    "ifrs-full:ComponentsOfEquityAxis": "ifrs-full:ReserveOfSharebasedPaymentsMember",
    "unit": "iso4217:USD"
   }
  },
  "f45521": {
   "value": "634498000",
   "decimals": -3,
   "dimensions": {
    "concept": "ifrs-full:Equity",
    "entity": "scheme:213800PDI9G7OUKLPV84",
    "period": "2021-01-01T00:00:00",
    "ifrs-full:ComponentsOfEquityAxis": "ifrs-full:RetainedEarningsMember",
    "unit": "iso4217:USD"
   }
  },
  "f45525": {
   "value": "1306648000",
   "decimals": -3,
   "dimensions": {
    "concept": "ifrs-full:Equity",
    "entity": "scheme:213800PDI9G7OUKLPV84",
    "period": "2021-01-01T00:00:00",
    "ifrs-full:ComponentsOfEquityAxis": "ifrs-full:EquityAttributableToOwnersOfParentMember",
    "unit": "iso4217:USD"
   }
  },
  "f45533": {
   "value": "-17196000",
   "decimals": -3,
   "dimensions": {
    "concept": "ifrs-full:Equity",
    "entity": "scheme:213800PDI9G7OUKLPV84",
    "period": "2021-01-01T00:00:00",
    "ifrs-full:ComponentsOfEquityAxis": "ifrs-full:NoncontrollingInterestsMember",
    "unit": "iso4217:USD"
   }
  },
  "f45542": {
   "value": "1289452000",
   "decimals": -3,
   "dimensions": {
    "concept": "ifrs-full:Equity",
    "entity": "scheme:213800PDI9G7OUKLPV84",
    "period": "2021-01-01T00:00:00",
    "unit": "iso4217:USD"
   }
  },
  "f45573": {
   "value": "2021-12-31",
   "dimensions": {
    "concept": "ifrs-full:DateOfEndOfReportingPeriod2013",
    "entity": "scheme:213800PDI9G7OUKLPV84",
    "period": "2021-01-01T00:00:00/2022-01-01T00:00:00"
   }
  },
  "f46987": {
   "value": "The Group is engaged in the business of exploration for and mining of precious metals, which represents three operating segments,two in the business of exploration and one in mining of precious metals.",
   "dimensions": {
    "concept": "ifrs-full:DescriptionOfNatureOfEntitysOperationsAndPrincipalActivities",
    "language": "en",
    "entity": "scheme:213800PDI9G7OUKLPV84",
    "period": "2021-01-01T00:00:00/2022-01-01T00:00:00"
   }
  },
  "f52398": {
   "value": "2 Mulcaster Street, St Helier, Jersey JE2 3NJ.",
   "dimensions": {
    "concept": "ifrs-full:AddressOfRegisteredOfficeOfEntity",
    "language": "en",
    "entity": "scheme:213800PDI9G7OUKLPV84",
    "period": "2021-01-01T00:00:00/2022-01-01T00:00:00"
   }
  },
  "f54859": {
   "value": "Centamin plc",
   "dimensions": {
    "concept": "ifrs-full:NameOfParentEntity",
    "language": "en",
    "entity": "scheme:213800PDI9G7OUKLPV84",
    "period": "2021-01-01T00:00:00/2022-01-01T00:00:00"
   }
  },
  "f54860": {
   "value": "Centamin plc",
   "dimensions": {
    "concept": "ifrs-full:NameOfReportingEntityOrOtherMeansOfIdentification",
    "language": "en",
    "entity": "scheme:213800PDI9G7OUKLPV84",
    "period": "2021-01-01T00:00:00/2022-01-01T00:00:00"
   }
  },
  "f54861": {
   "value": "listed public company",
   "dimensions": {
    "concept": "ifrs-full:LegalFormOfEntity",
    "language": "en",
    "entity": "scheme:213800PDI9G7OUKLPV84",
    "period": "2021-01-01T00:00:00/2022-01-01T00:00:00"
   }
  },
  "f54863": {
   "value": "Jersey",
   "dimensions": {
    "concept": "ifrs-full:CountryOfIncorporation",
    "language": "en",
    "entity": "scheme:213800PDI9G7OUKLPV84",
    "period": "2021-01-01T00:00:00/2022-01-01T00:00:00"
   }
  },
  "f54864": {
   "value": "Jersey",
   "dimensions": {
    "concept": "ifrs-full:DomicileOfEntity",
    "language": "en",
    "entity": "scheme:213800PDI9G7OUKLPV84",
    "period": "2021-01-01T00:00:00/2022-01-01T00:00:00"
   }
  },
  "f54872": {
   "value": "Jersey",
   "dimensions": {
    "concept": "ifrs-full:PrincipalPlaceOfBusiness",
    "language": "en",
    "entity": "scheme:213800PDI9G7OUKLPV84",
    "period": "2021-01-01T00:00:00/2022-01-01T00:00:00"
   }
  }
 }
}