{
 "documentInfo": {
  "documentType": "https://xbrl.org/2021/xbrl-json",
  "features": {
   "xbrl:canonicalValues": true
  },
  "namespaces": {
   "SJ\u00d3": "http://sjova.is/2021-12-31",
   "ifrs-full": "http://xbrl.ifrs.org/taxonomy/2020-03-16/ifrs-full",
   "iso4217": "http://www.xbrl.org/2003/iso4217",
   "scheme": "http://standards.iso.org/iso/17442",
   "xbrl": "https://xbrl.org/2021",
   "xbrli": "http://www.xbrl.org/2003/instance"
  },
  "taxonomy": [
   "http://sjova.is/2021-12-31/213800R3IXBON2LBEI63-2021-12-31.xsd"
  ]
 },
 "facts": {
  "pp-value-1": {
   "value": "Sj\u00f3v\u00e1-Almennartryggingar hf.",
   "dimensions": {
    "concept": "ifrs-full:NameOfReportingEntityOrOtherMeansOfIdentification",
    "language": "is",
    "entity": "scheme:213800R3IXBON2LBEI63",
    "period": "2021-01-01T00:00:00/2022-01-01T00:00:00"
   }
  },
  "f29": {
   "value": "Kringlunni 5",
   "dimensions": {
    "concept": "ifrs-full:AddressOfRegisteredOfficeOfEntity",
    "language": "is",
    "entity": "scheme:213800R3IXBON2LBEI63",
    "period": "2021-01-01T00:00:00/2022-01-01T00:00:00"
   }
  },
  "pp-value-5": {
   "value": "Sj\u00f3v\u00e1-Almennra trygginga hf.",
   "dimensions": {
    "concept": "ifrs-full:NameOfParentEntity",
    "language": "is",
    "entity": "scheme:213800R3IXBON2LBEI63",
    "period": "2021-01-01T00:00:00/2022-01-01T00:00:00"
   }
  },
  "f280": {
   "value": "tryggingaf\u00e9lag",
   "dimensions": {
    "concept": "ifrs-full:DescriptionOfNatureOfEntitysOperationsAndPrincipalActivities",
    "language": "is",
    "entity": "scheme:213800R3IXBON2LBEI63",
    "period": "2021-01-01T00:00:00/2022-01-01T00:00:00"
   }
  },
  "f289": {
   "value": "\u00cdsland",
   "dimensions": {
    "concept": "ifrs-full:CountryOfIncorporation",
    "language": "is",
    "entity": "scheme:213800R3IXBON2LBEI63",
    "period": "2021-01-01T00:00:00/2022-01-01T00:00:00"
   }
  },
  "f1643": {
   "value": "Sj\u00f3v\u00e1-Almennra trygginga hf",
   "dimensions": {
    "concept": "ifrs-full:NameOfUltimateParentOfGroup",
    "language": "is",
    "entity": "scheme:213800R3IXBON2LBEI63",
    "period": "2021-01-01T00:00:00/2022-01-01T00:00:00"
   }
  },
  "f5518": {
   "value": "23952628000",
   "decimals": -3,
   "dimensions": {
    "concept": "SJ\u00d3:GrossPremiumsWritten",
    "entity": "scheme:213800R3IXBON2LBEI63",
    "period": "2021-01-01T00:00:00/2022-01-01T00:00:00",
    "unit": "iso4217:ISK"
   }
  },
  "f5522": {
   "value": "20831290000",
   "decimals": -3,
   "dimensions": {
    "concept": "SJ\u00d3:GrossPremiumsWritten",
    "entity": "scheme:213800R3IXBON2LBEI63",
    "period": "2020-01-01T00:00:00/2021-01-01T00:00:00",
    "unit": "iso4217:ISK"
   }
  },
  "f5527": {
   "value": "1024858000",
   "decimals": -3,
   "dimensions": {
    "concept": "SJ\u00d3:CededReinsurancePremiums",
    "entity": "scheme:213800R3IXBON2LBEI63",
    "period": "2021-01-01T00:00:00/2022-01-01T00:00:00",
    "unit": "iso4217:ISK"
   }
  },
  "f5532": {
   "value": "1014584000",
   "decimals": -3,
   "dimensions": {
    "concept": "SJ\u00d3:CededReinsurancePremiums",
    "entity": "scheme:213800R3IXBON2LBEI63",
    "period": "2020-01-01T00:00:00/2021-01-01T00:00:00",
    "unit": "iso4217:ISK"
   }
  },
  "f5540": {
   "value": "22927769000",
   "decimals": -3,
   "dimensions": {
    "concept": "ifrs-full:NetEarnedPremium",
    "entity": "scheme:213800R3IXBON2LBEI63",
    "period": "2021-01-01T00:00:00/2022-01-01T00:00:00",
    "unit": "iso4217:ISK"
   }
  },
  "f5544": {
   "value": "19816706000",
   "decimals": -3,
   "dimensions": {
    "concept": "ifrs-full:NetEarnedPremium",
    "entity": "scheme:213800R3IXBON2LBEI63",
    "period": "2020-01-01T00:00:00/2021-01-01T00:00:00",
    "unit": "iso4217:ISK"
   }
  },
  "f5548": {
   "value": "496659000",
   "decimals": -3,
   "dimensions": {
    "concept": "ifrs-full:FinanceIncome",
    "entity": "scheme:213800R3IXBON2LBEI63",
    "period": "2021-01-01T00:00:00/2022-01-01T00:00:00",
    "unit": "iso4217:ISK"
   }
  },
  "f5551": {
   "value": "475778000",
   "decimals": -3,
   "dimensions": {
    "concept": "ifrs-full:FinanceIncome",
    "entity": "scheme:213800R3IXBON2LBEI63",
    "period": "2020-01-01T00:00:00/2021-01-01T00:00:00",
    "unit": "iso4217:ISK"
   }
  },
  "f5554": {
   "value": "7887528000",
   "decimals": -3,
   "dimensions": {
    "concept": "ifrs-full:GainsLossesOnFinancialAssetsAtFairValueThroughProfitOrLoss",
    "entity": "scheme:213800R3IXBON2LBEI63",
    "period": "2021-01-01T00:00:00/2022-01-01T00:00:00",
    "unit": "iso4217:ISK"
   }
  },
  "f5557": {
   "value": "4798578000",
   "decimals": -3,
   "dimensions": {
    "concept": "ifrs-full:GainsLossesOnFinancialAssetsAtFairValueThroughProfitOrLoss",
    "entity": "scheme:213800R3IXBON2LBEI63",
    "period": "2020-01-01T00:00:00/2021-01-01T00:00:00",
    "unit": "iso4217:ISK"
   }
  },
  "f5562": {
   "value": "8384187000",
   "decimals": -3,
   "dimensions": {
    "concept": "ifrs-full:InvestmentIncome",
    "entity": "scheme:213800R3IXBON2LBEI63",
    "period": "2021-01-01T00:00:00/2022-01-01T00:00:00",
    "unit": "iso4217:ISK"
   }
  },
  "f5565": {
   "value": "5274357000",
   "decimals": -3,
   "dimensions": {
    "concept": "ifrs-full:InvestmentIncome",
    "entity": "scheme:213800R3IXBON2LBEI63",
    "period": "2020-01-01T00:00:00/2021-01-01T00:00:00",
    "unit": "iso4217:ISK"
   }
  },
  "f5568": {
   "value": "117415000",
   "decimals": -3,
   "dimensions": {
    "concept": "ifrs-full:FeeAndCommissionIncome",
    "entity": "scheme:213800R3IXBON2LBEI63",
    "period": "2021-01-01T00:00:00/2022-01-01T00:00:00",
    "unit": "iso4217:ISK"
   }
  },
  "f5571": {
   "value": "101427000",
   "decimals": -3,
   "dimensions": {
    "concept": "ifrs-full:FeeAndCommissionIncome",
    "entity": "scheme:213800R3IXBON2LBEI63",
    "period": "2020-01-01T00:00:00/2021-01-01T00:00:00",
    "unit": "iso4217:ISK"
   }
  },
  "f5574": {
   "value": "124184000",
   "decimals": -3,
   "dimensions": {
    "concept": "ifrs-full:MiscellaneousOtherOperatingIncome",
    "entity": "scheme:213800R3IXBON2LBEI63",
    "period": "2021-01-01T00:00:00/2022-01-01T00:00:00",
    "unit": "iso4217:ISK"
   }
  },
  "f5577": {
   "value": "116175000",
   "decimals": -3,
   "dimensions": {
    "concept": "ifrs-full:MiscellaneousOtherOperatingIncome",
    "entity": "scheme:213800R3IXBON2LBEI63",
    "period": "2020-01-01T00:00:00/2021-01-01T00:00:00",
    "unit": "iso4217:ISK"
   }
  },
  "f5580": {
   "value": "241599000",
   "decimals": -3,
   "dimensions": {
    "concept": "ifrs-full:OtherIncome",
    "entity": "scheme:213800R3IXBON2LBEI63",
    "period": "2021-01-01T00:00:00/2022-01-01T00:00:00",
    "unit": "iso4217:ISK"
   }
  },
  "f5583": {
   "value": "217602000",
   "decimals": -3,
   "dimensions": {
    "concept": "ifrs-full:OtherIncome",
    "entity": "scheme:213800R3IXBON2LBEI63",
    "period": "2020-01-01T00:00:00/2021-01-01T00:00:00",
    "unit": "iso4217:ISK"
   }
  },
  "f5586": {
   "value": "31553555000",
   "decimals": -3,
   "dimensions": {
    "concept": "ifrs-full:RevenueAndOperatingIncome",
    "entity": "scheme:213800R3IXBON2LBEI63",
    "period": "2021-01-01T00:00:00/2022-01-01T00:00:00",
    "unit": "iso4217:ISK"
   }
  },
  "f5590": {
   "value": "25308665000",
   "decimals": -3,
   "dimensions": {
    "concept": "ifrs-full:RevenueAndOperatingIncome",
    "entity": "scheme:213800R3IXBON2LBEI63",
    "period": "2020-01-01T00:00:00/2021-01-01T00:00:00",
    "unit": "iso4217:ISK"
   }
  },
  "f5594": {
   "value": "16555963000",
   "decimals": -3,
   "dimensions": {
    "concept": "SJ\u00d3:ClaimsAndBenefitsPaid",
    "entity": "scheme:213800R3IXBON2LBEI63",
    "period": "2021-01-01T00:00:00/2022-01-01T00:00:00",
    "unit": "iso4217:ISK"
   }
  },
  "f5600": {
   "value": "14719626000",
   "decimals": -3,
   "dimensions": {
    "concept": "SJ\u00d3:ClaimsAndBenefitsPaid",
    "entity": "scheme:213800R3IXBON2LBEI63",
    "period": "2020-01-01T00:00:00/2021-01-01T00:00:00",
    "unit": "iso4217:ISK"
   }
  },
  "f5605": {
   "value": "249061000",
   "decimals": -3,
   "dimensions": {
    "concept": "ifrs-full:IncomeFromAmountsRecoveredFromReinsurer",
    "entity": "scheme:213800R3IXBON2LBEI63",
    "period": "2021-01-01T00:00:00/2022-01-01T00:00:00",
    "unit": "iso4217:ISK"
   }
  },
  "f5608": {
   "value": "496325000",
   "decimals": -3,
   "dimensions": {
    "concept": "ifrs-full:IncomeFromAmountsRecoveredFromReinsurer",
    "entity": "scheme:213800R3IXBON2LBEI63",
    "period": "2020-01-01T00:00:00/2021-01-01T00:00:00",
    "unit": "iso4217:ISK"
   }
  },
  "f5615": {
   "value": "16306902000",
   "decimals": -3,
   "dimensions": {
    "concept": "ifrs-full:ClaimsAndBenefitsPaidNetOfReinsuranceRecoveries",
    "entity": "scheme:213800R3IXBON2LBEI63",
    "period": "2021-01-01T00:00:00/2022-01-01T00:00:00",
    "unit": "iso4217:ISK"
   }
  },
  "f5621": {
   "value": "14223301000",
   "decimals": -3,
   "dimensions": {
    "concept": "ifrs-full:ClaimsAndBenefitsPaidNetOfReinsuranceRecoveries",
    "entity": "scheme:213800R3IXBON2LBEI63",
    "period": "2020-01-01T00:00:00/2021-01-01T00:00:00",
    "unit": "iso4217:ISK"
   }
  },
  "f5626": {
   "value": "-99080000",
   "decimals": -3,
   "dimensions": {
    "concept": "ifrs-full:IncreaseDecreaseInInsuranceLiabilitiesNetOfReinsurance",
    "entity": "scheme:213800R3IXBON2LBEI63",
    "period": "2021-01-01T00:00:00/2022-01-01T00:00:00",
    "unit": "iso4217:ISK"
   }
  },
  "f5629": {
   "value": "677988000",
   "decimals": -3,
   "dimensions": {
    "concept": "ifrs-full:IncreaseDecreaseInInsuranceLiabilitiesNetOfReinsurance",
    "entity": "scheme:213800R3IXBON2LBEI63",
    "period": "2020-01-01T00:00:00/2021-01-01T00:00:00",
    "unit": "iso4217:ISK"
   }
  },
  "f5635": {
   "value": "4998430000",
   "decimals": -3,
   "dimensions": {
    "concept": "ifrs-full:OperatingExpense",
    "entity": "scheme:213800R3IXBON2LBEI63",
    "period": "2021-01-01T00:00:00/2022-01-01T00:00:00",
    "unit": "iso4217:ISK"
   }
  },
  "f5640": {
   "value": "4479092000",
   "decimals": -3,
   "dimensions": {
    "concept": "ifrs-full:OperatingExpense",
    "entity": "scheme:213800R3IXBON2LBEI63",
    "period": "2020-01-01T00:00:00/2021-01-01T00:00:00",
    "unit": "iso4217:ISK"
   }
  },
  "f5645": {
   "value": "21206252000",
   "decimals": -3,
   "dimensions": {
    "concept": "ifrs-full:ExpenseByNature",
    "entity": "scheme:213800R3IXBON2LBEI63",
    "period": "2021-01-01T00:00:00/2022-01-01T00:00:00",
    "unit": "iso4217:ISK"
   }
  },
  "f5650": {
   "value": "19380381000",
   "decimals": -3,
   "dimensions": {
    "concept": "ifrs-full:ExpenseByNature",
    "entity": "scheme:213800R3IXBON2LBEI63",
    "period": "2020-01-01T00:00:00/2021-01-01T00:00:00",
    "unit": "iso4217:ISK"
   }
  },
  "f5655": {
   "value": "10347303000",
   "decimals": -3,
   "dimensions": {
    "concept": "ifrs-full:ProfitLossBeforeTax",
    "entity": "scheme:213800R3IXBON2LBEI63",
    "period": "2021-01-01T00:00:00/2022-01-01T00:00:00",
    "unit": "iso4217:ISK"
   }
  },
  "f5659": {
   "value": "5928285000",
   "decimals": -3,
   "dimensions": {
    "concept": "ifrs-full:ProfitLossBeforeTax",
    "entity": "scheme:213800R3IXBON2LBEI63",
    "period": "2020-01-01T00:00:00/2021-01-01T00:00:00",
    "unit": "iso4217:ISK"
   }
  },
  "f5664": {
   "value": "777695000",
   "decimals": -3,
   "dimensions": {
    "concept": "ifrs-full:IncomeTaxExpenseContinuingOperations",
    "entity": "scheme:213800R3IXBON2LBEI63",
    "period": "2021-01-01T00:00:00/2022-01-01T00:00:00",
    "unit": "iso4217:ISK"
   }
  },
  "f5669": {
   "value": "608298000",
   "decimals": -3,
   "dimensions": {
    "concept": "ifrs-full:IncomeTaxExpenseContinuingOperations",
    "entity": "scheme:213800R3IXBON2LBEI63",
    "period": "2020-01-01T00:00:00/2021-01-01T00:00:00",
    "unit": "iso4217:ISK"
   }
  },
  "f5674": {
   "value": "9569608000",
   "decimals": -3,
   "dimensions": {
    "concept": "ifrs-full:ComprehensiveIncome",
    "entity": "scheme:213800R3IXBON2LBEI63",
    "period": "2021-01-01T00:00:00/2022-01-01T00:00:00",
    "unit": "iso4217:ISK"
   }
  },
  "f5677": {
   "value": "5319986000",
   "decimals": -3,
   "dimensions": {
    "concept": "ifrs-full:ComprehensiveIncome",
    "entity": "scheme:213800R3IXBON2LBEI63",
    "period": "2020-01-01T00:00:00/2021-01-01T00:00:00",
    "unit": "iso4217:ISK"
   }
  },
  "f5683": {
   "value": "9569608000",
   "decimals": -3,
   "dimensions": {
    "concept": "ifrs-full:ProfitLossAttributableToOwnersOfParent",
    "entity": "scheme:213800R3IXBON2LBEI63",
    "period": "2021-01-01T00:00:00/2022-01-01T00:00:00",
    "unit": "iso4217:ISK"
   }
  },
  "f5686": {
   "value": "5319986000",
   "decimals": -3,
   "dimensions": {
    "concept": "ifrs-full:ProfitLossAttributableToOwnersOfParent",
    "entity": "scheme:213800R3IXBON2LBEI63",
    "period": "2020-01-01T00:00:00/2021-01-01T00:00:00",
    "unit": "iso4217:ISK"
   }
  },
  "f5692": {
   "value": "7.34",
   "decimals": 2,
   "dimensions": {
    "concept": "ifrs-full:BasicAndDilutedEarningsLossPerShare",
    "entity": "scheme:213800R3IXBON2LBEI63",
    "period": "2021-01-01T00:00:00/2022-01-01T00:00:00",
    "unit": "iso4217:ISK/xbrli:shares"
   }
  },
  "f5695": {
   "value": "3.98",
   "decimals": 2,
   "dimensions": {
    "concept": "ifrs-full:BasicAndDilutedEarningsLossPerShare",
    "entity": "scheme:213800R3IXBON2LBEI63",
    "period": "2020-01-01T00:00:00/2021-01-01T00:00:00",
    "unit": "iso4217:ISK/xbrli:shares"
   }
  },
  "f5830": {
   "value": "477635000",
   "decimals": -3,
   "dimensions": {
    "concept": "ifrs-full:PropertyPlantAndEquipment",
    "entity": "scheme:213800R3IXBON2LBEI63",
    "period": "2022-01-01T00:00:00",
    "unit": "iso4217:ISK"
   }
  },
  "f5833": {
   "value": "492656000",
   "decimals": -3,
   "dimensions": {
    "concept": "ifrs-full:PropertyPlantAndEquipment",
    "entity": "scheme:213800R3IXBON2LBEI63",
    "period": "2021-01-01T00:00:00",
    "unit": "iso4217:ISK"
   }
  },
  "f5838": {
   "value": "1292373000",
   "decimals": -3,
   "dimensions": {
    "concept": "ifrs-full:RightofuseAssets",
    "entity": "scheme:213800R3IXBON2LBEI63",
    "period": "2022-01-01T00:00:00",
    "unit": "iso4217:ISK"
   }
  },
  "f5841": {
   "value": "275970000",
   "decimals": -3,
   "dimensions": {
    "concept": "ifrs-full:RightofuseAssets",
    "entity": "scheme:213800R3IXBON2LBEI63",
    "period": "2021-01-01T00:00:00",
    "unit": "iso4217:ISK"
   }
  },
  "f5846": {
   "value": "243578000",
   "decimals": -3,
   "dimensions": {
    "concept": "ifrs-full:Goodwill",
    "entity": "scheme:213800R3IXBON2LBEI63",
    "period": "2022-01-01T00:00:00",
    "unit": "iso4217:ISK"
   }
  },
  "f5849": {
   "value": "243578000",
   "decimals": -3,
   "dimensions": {
    "concept": "ifrs-full:Goodwill",
    "entity": "scheme:213800R3IXBON2LBEI63",
    "period": "2021-01-01T00:00:00",
    "unit": "iso4217:ISK"
   }
  },
  "f5853": {
   "value": "352000",
   "decimals": -3,
   "dimensions": {
    "concept": "ifrs-full:IntangibleAssetsOtherThanGoodwill",
    "entity": "scheme:213800R3IXBON2LBEI63",
    "period": "2022-01-01T00:00:00",
    "unit": "iso4217:ISK"
   }
  },
  "f5857": {
   "value": "1200000",
   "decimals": -3,
   "dimensions": {
    "concept": "ifrs-full:IntangibleAssetsOtherThanGoodwill",
    "entity": "scheme:213800R3IXBON2LBEI63",
    "period": "2021-01-01T00:00:00",
    "unit": "iso4217:ISK"
   }
  },
  "f5862": {
   "value": "2392000",
   "decimals": -3,
   "dimensions": {
    "concept": "ifrs-full:DeferredTaxAssets",
    "entity": "scheme:213800R3IXBON2LBEI63",
    "period": "2022-01-01T00:00:00",
    "unit": "iso4217:ISK"
   }
  },
  "f5865": {
   "value": "2522000",
   "decimals": -3,
   "dimensions": {
    "concept": "ifrs-full:DeferredTaxAssets",
    "entity": "scheme:213800R3IXBON2LBEI63",
    "period": "2021-01-01T00:00:00",
    "unit": "iso4217:ISK"
   }
  },
  "f5869": {
   "value": "50836062000",
   "decimals": -3,
   "dimensions": {
    "concept": "ifrs-full:FinancialAssetsAtFairValueThroughProfitOrLoss",
    "entity": "scheme:213800R3IXBON2LBEI63",
    "period": "2022-01-01T00:00:00",
    "unit": "iso4217:ISK"
   }
  },
  "f5873": {
   "value": "43782883000",
   "decimals": -3,
   "dimensions": {
    "concept": "ifrs-full:FinancialAssetsAtFairValueThroughProfitOrLoss",
    "entity": "scheme:213800R3IXBON2LBEI63",
    "period": "2021-01-01T00:00:00",
    "unit": "iso4217:ISK"
   }
  },
  "f5879": {
   "value": "6062149000",
   "decimals": -3,
   "dimensions": {
    "concept": "ifrs-full:InvestmentsForRiskOfPolicyholders",
    "entity": "scheme:213800R3IXBON2LBEI63",
    "period": "2022-01-01T00:00:00",
    "unit": "iso4217:ISK"
   }
  },
  "f5882": {
   "value": "5305346000",
   "decimals": -3,
   "dimensions": {
    "concept": "ifrs-full:InvestmentsForRiskOfPolicyholders",
    "entity": "scheme:213800R3IXBON2LBEI63",
    "period": "2021-01-01T00:00:00",
    "unit": "iso4217:ISK"
   }
  },
  "f5887": {
   "value": "934997000",
   "decimals": -3,
   "dimensions": {
    "concept": "ifrs-full:ReinsuranceAssets",
    "entity": "scheme:213800R3IXBON2LBEI63",
    "period": "2022-01-01T00:00:00",
    "unit": "iso4217:ISK"
   }
  },
  "f5890": {
   "value": "1268767000",
   "decimals": -3,
   "dimensions": {
    "concept": "ifrs-full:ReinsuranceAssets",
    "entity": "scheme:213800R3IXBON2LBEI63",
    "period": "2021-01-01T00:00:00",
    "unit": "iso4217:ISK"
   }
  },
  "f5895": {
   "value": "6911977000",
   "decimals": -3,
   "dimensions": {
    "concept": "ifrs-full:TradeAndOtherReceivables",
    "entity": "scheme:213800R3IXBON2LBEI63",
    "period": "2022-01-01T00:00:00",
    "unit": "iso4217:ISK"
   }
  },
  "f5898": {
   "value": "6728055000",
   "decimals": -3,
   "dimensions": {
    "concept": "ifrs-full:TradeAndOtherReceivables",
    "entity": "scheme:213800R3IXBON2LBEI63",
    "period": "2021-01-01T00:00:00",
    "unit": "iso4217:ISK"
   }
  },
  "f5901": {
   "value": "1094896000",
   "decimals": -3,
   "dimensions": {
    "concept": "ifrs-full:CashAndCashEquivalents",
    "entity": "scheme:213800R3IXBON2LBEI63",
    "period": "2022-01-01T00:00:00",
    "unit": "iso4217:ISK"
   }
  },
  "f5904": {
   "value": "1160223000",
   "decimals": -3,
   "dimensions": {
    "concept": "ifrs-full:CashAndCashEquivalents",
    "entity": "scheme:213800R3IXBON2LBEI63",
    "period": "2021-01-01T00:00:00",
    "unit": "iso4217:ISK"
   }
  },
  "f5907": {
   "value": "67856411000",
   "decimals": -3,
   "dimensions": {
    "concept": "ifrs-full:Assets",
    "entity": "scheme:213800R3IXBON2LBEI63",
    "period": "2022-01-01T00:00:00",
    "unit": "iso4217:ISK"
   }
  },
  "f5911": {
   "value": "59261201000",
   "decimals": -3,
   "dimensions": {
    "concept": "ifrs-full:Assets",
    "entity": "scheme:213800R3IXBON2LBEI63",
    "period": "2021-01-01T00:00:00",
    "unit": "iso4217:ISK"
   }
  },
  "f5918": {
   "value": "1227796000",
   "decimals": -3,
   "dimensions": {
    "concept": "ifrs-full:IssuedCapital",
    "entity": "scheme:213800R3IXBON2LBEI63",
    "period": "2022-01-01T00:00:00",
    "unit": "iso4217:ISK"
   }
  },
  "f5921": {
   "value": "1334106000",
   "decimals": -3,
   "dimensions": {
    "concept": "ifrs-full:IssuedCapital",
    "entity": "scheme:213800R3IXBON2LBEI63",
    "period": "2021-01-01T00:00:00",
    "unit": "iso4217:ISK"
   }
  },
  "f5926": {
   "value": "2274856000",
   "decimals": -3,
   "dimensions": {
    "concept": "ifrs-full:SharePremium",
    "entity": "scheme:213800R3IXBON2LBEI63",
    "period": "2022-01-01T00:00:00",
    "unit": "iso4217:ISK"
   }
  },
  "f5929": {
   "value": "6110625000",
   "decimals": -3,
   "dimensions": {
    "concept": "ifrs-full:SharePremium",
    "entity": "scheme:213800R3IXBON2LBEI63",
    "period": "2021-01-01T00:00:00",
    "unit": "iso4217:ISK"
   }
  },
  "f5934": {
   "value": "6722578000",
   "decimals": -3,
   "dimensions": {
    "concept": "ifrs-full:OtherReserves",
    "entity": "scheme:213800R3IXBON2LBEI63",
    "period": "2022-01-01T00:00:00",
    "unit": "iso4217:ISK"
   }
  },
  "f5937": {
   "value": "732834000",
   "decimals": -3,
   "dimensions": {
    "concept": "ifrs-full:OtherReserves",
    "entity": "scheme:213800R3IXBON2LBEI63",
    "period": "2021-01-01T00:00:00",
    "unit": "iso4217:ISK"
   }
  },
  "f5940": {
   "value": "14113559000",
   "decimals": -3,
   "dimensions": {
    "concept": "ifrs-full:RetainedEarnings",
    "entity": "scheme:213800R3IXBON2LBEI63",
    "period": "2022-01-01T00:00:00",
    "unit": "iso4217:ISK"
   }
  },
  "f5944": {
   "value": "13185993000",
   "decimals": -3,
   "dimensions": {
    "concept": "ifrs-full:RetainedEarnings",
    "entity": "scheme:213800R3IXBON2LBEI63",
    "period": "2021-01-01T00:00:00",
    "unit": "iso4217:ISK"
   }
  },
  "f5949": {
   "value": "24338788000",
   "decimals": -3,
   "dimensions": {
    "concept": "ifrs-full:Equity",
    "entity": "scheme:213800R3IXBON2LBEI63",
    "period": "2022-01-01T00:00:00",
    "unit": "iso4217:ISK"
   }
  },
  "f5953": {
   "value": "21363559000",
   "decimals": -3,
   "dimensions": {
    "concept": "ifrs-full:Equity",
    "entity": "scheme:213800R3IXBON2LBEI63",
    "period": "2021-01-01T00:00:00",
    "unit": "iso4217:ISK"
   }
  },
  "f5962": {
   "value": "33341268000",
   "decimals": -3,
   "dimensions": {
    "concept": "ifrs-full:LiabilitiesArisingFromInsuranceContracts",
    "entity": "scheme:213800R3IXBON2LBEI63",
    "period": "2022-01-01T00:00:00",
    "unit": "iso4217:ISK"
   }
  },
  "f5966": {
   "value": "29866524000",
   "decimals": -3,
   "dimensions": {
    "concept": "ifrs-full:LiabilitiesArisingFromInsuranceContracts",
    "entity": "scheme:213800R3IXBON2LBEI63",
    "period": "2021-01-01T00:00:00",
    "unit": "iso4217:ISK"
   }
  },
  "f5972": {
   "value": "6062149000",
   "decimals": -3,
   "dimensions": {
    "concept": "ifrs-full:InvestmentContractsLiabilities",
    "entity": "scheme:213800R3IXBON2LBEI63",
    "period": "2022-01-01T00:00:00",
    "unit": "iso4217:ISK"
   }
  },
  "f5975": {
   "value": "5305346000",
   "decimals": -3,
   "dimensions": {
    "concept": "ifrs-full:InvestmentContractsLiabilities",
    "entity": "scheme:213800R3IXBON2LBEI63",
    "period": "2021-01-01T00:00:00",
    "unit": "iso4217:ISK"
   }
  },
  "f5984": {
   "value": "1321270000",
   "decimals": -3,
   "dimensions": {
    "concept": "ifrs-full:LeaseLiabilities",
    "entity": "scheme:213800R3IXBON2LBEI63",
    "period": "2022-01-01T00:00:00",
    "unit": "iso4217:ISK"
   }
  },
  "f5987": {
   "value": "288904000",
   "decimals": -3,
   "dimensions": {
    "concept": "ifrs-full:LeaseLiabilities",
    "entity": "scheme:213800R3IXBON2LBEI63",
    "period": "2021-01-01T00:00:00",
    "unit": "iso4217:ISK"
   }
  },
  "f5990": {
   "value": "799589000",
   "decimals": -3,
   "dimensions": {
    "concept": "ifrs-full:CurrentTaxLiabilities",
    "entity": "scheme:213800R3IXBON2LBEI63",
    "period": "2022-01-01T00:00:00",
    "unit": "iso4217:ISK"
   }
  },
  "f5993": {
   "value": "604195000",
   "decimals": -3,
   "dimensions": {
    "concept": "ifrs-full:CurrentTaxLiabilities",
    "entity": "scheme:213800R3IXBON2LBEI63",
    "period": "2021-01-01T00:00:00",
    "unit": "iso4217:ISK"
   }
  },
  "f5998": {
   "value": "1993346000",
   "decimals": -3,
   "dimensions": {
    "concept": "ifrs-full:TradeAndOtherPayables",
    "entity": "scheme:213800R3IXBON2LBEI63",
    "period": "2022-01-01T00:00:00",
    "unit": "iso4217:ISK"
   }
  },
  "f6001": {
   "value": "1832673000",
   "decimals": -3,
   "dimensions": {
    "concept": "ifrs-full:TradeAndOtherPayables",
    "entity": "scheme:213800R3IXBON2LBEI63",
    "period": "2021-01-01T00:00:00",
    "unit": "iso4217:ISK"
   }
  },
  "f6004": {
   "value": "43517623000",
   "decimals": -3,
   "dimensions": {
    "concept": "ifrs-full:Liabilities",
    "entity": "scheme:213800R3IXBON2LBEI63",
    "period": "2022-01-01T00:00:00",
    "unit": "iso4217:ISK"
   }
  },
  "f6008": {
   "value": "37897642000",
   "decimals": -3,
   "dimensions": {
    "concept": "ifrs-full:Liabilities",
    "entity": "scheme:213800R3IXBON2LBEI63",
    "period": "2021-01-01T00:00:00",
    "unit": "iso4217:ISK"
   }
  },
  "f6012": {
   "value": "67856411000",
   "decimals": -3,
   "dimensions": {
    "concept": "ifrs-full:EquityAndLiabilities",
    "entity": "scheme:213800R3IXBON2LBEI63",
    "period": "2022-01-01T00:00:00",
    "unit": "iso4217:ISK"
   }
  },
  "f6016": {
   "value": "59261201000",
   "decimals": -3,
   "dimensions": {
    "concept": "ifrs-full:EquityAndLiabilities",
    "entity": "scheme:213800R3IXBON2LBEI63",
    "period": "2021-01-01T00:00:00",
    "unit": "iso4217:ISK"
   }
  },
  "f6185": {
   "value": "1334106000",
   "decimals": -3,
   "dimensions": {
    "concept": "ifrs-full:Equity",
    "entity": "scheme:213800R3IXBON2LBEI63",
    "period": "2021-01-01T00:00:00",
    "ifrs-full:ComponentsOfEquityAxis": "ifrs-full:IssuedCapitalMember",
    "unit": "iso4217:ISK"
   }
  },
  "f6188": {
   "value": "6110625000",
   "decimals": -3,
   "dimensions": {
    "concept": "ifrs-full:Equity",
    "entity": "scheme:213800R3IXBON2LBEI63",
    "period": "2021-01-01T00:00:00",
    "ifrs-full:ComponentsOfEquityAxis": "ifrs-full:SharePremiumMember",
    "unit": "iso4217:ISK"
   }
  },
  "f6191": {
   "value": "732834000",
   "decimals": -3,
   "dimensions": {
    "concept": "ifrs-full:Equity",
    "entity": "scheme:213800R3IXBON2LBEI63",
    "period": "2021-01-01T00:00:00",
    "ifrs-full:ComponentsOfEquityAxis": "ifrs-full:OtherReservesMember",
    "unit": "iso4217:ISK"
   }
  },
  "f6194": {
   "value": "13185993000",
   "decimals": -3,
   "dimensions": {
    "concept": "ifrs-full:Equity",
    "entity": "scheme:213800R3IXBON2LBEI63",
    "period": "2021-01-01T00:00:00",
    "ifrs-full:ComponentsOfEquityAxis": "ifrs-full:RetainedEarningsMember",
    "unit": "iso4217:ISK"
   }
  },
  "f6198": {
   "value": "21363559000",
   "decimals": -3,
   "dimensions": {
    "concept": "ifrs-full:Equity",
    "entity": "scheme:213800R3IXBON2LBEI63",
    "period": "2021-01-01T00:00:00",
    "unit": "iso4217:ISK"
   }
  },
  "f6203": {
   "value": "2652298000",
   "decimals": -3,
   "dimensions": {
    "concept": "ifrs-full:DividendsPaid",
    "entity": "scheme:213800R3IXBON2LBEI63",
    "period": "2021-01-01T00:00:00/2022-01-01T00:00:00",
    "ifrs-full:ComponentsOfEquityAxis": "ifrs-full:RetainedEarningsMember",
    "unit": "iso4217:ISK"
   }
  },
  "f6207": {
   "value": "2652298000",
   "decimals": -3,
   "dimensions": {
    "concept": "ifrs-full:DividendsPaid",
    "entity": "scheme:213800R3IXBON2LBEI63",
    "period": "2021-01-01T00:00:00/2022-01-01T00:00:00",
    "unit": "iso4217:ISK"
   }
  },
  "f6212": {
   "value": "39821000",
   "decimals": -3,
   "dimensions": {
    "concept": "ifrs-full:PurchaseOfTreasuryShares",
    "entity": "scheme:213800R3IXBON2LBEI63",
    "period": "2021-01-01T00:00:00/2022-01-01T00:00:00",
    "ifrs-full:ComponentsOfEquityAxis": "ifrs-full:IssuedCapitalMember",
    "unit": "iso4217:ISK"
   }
  },
  "f6217": {
   "value": "1402259000",
   "decimals": -3,
   "dimensions": {
    "concept": "ifrs-full:PurchaseOfTreasuryShares",
    "entity": "scheme:213800R3IXBON2LBEI63",
    "period": "2021-01-01T00:00:00/2022-01-01T00:00:00",
    "ifrs-full:ComponentsOfEquityAxis": "ifrs-full:SharePremiumMember",
    "unit": "iso4217:ISK"
   }
  },
  "f6221": {
   "value": "1442081000",
   "decimals": -3,
   "dimensions": {
    "concept": "ifrs-full:PurchaseOfTreasuryShares",
    "entity": "scheme:213800R3IXBON2LBEI63",
    "period": "2021-01-01T00:00:00/2022-01-01T00:00:00",
    "unit": "iso4217:ISK"
   }
  },
  "f6226": {
   "value": "66489000",
   "decimals": -3,
   "dimensions": {
    "concept": "ifrs-full:ReductionOfIssuedCapital",
    "entity": "scheme:213800R3IXBON2LBEI63",
    "period": "2021-01-01T00:00:00/2022-01-01T00:00:00",
    "ifrs-full:ComponentsOfEquityAxis": "ifrs-full:IssuedCapitalMember",
    "unit": "iso4217:ISK"
   }
  },
  "f6231": {
   "value": "2433510000",
   "decimals": -3,
   "dimensions": {
    "concept": "ifrs-full:ReductionOfIssuedCapital",
    "entity": "scheme:213800R3IXBON2LBEI63",
    "period": "2021-01-01T00:00:00/2022-01-01T00:00:00",
    "ifrs-full:ComponentsOfEquityAxis": "ifrs-full:SharePremiumMember",
    "unit": "iso4217:ISK"
   }
  },
  "f6235": {
   "value": "2500000000",
   "decimals": -3,
   "dimensions": {
    "concept": "ifrs-full:ReductionOfIssuedCapital",
    "entity": "scheme:213800R3IXBON2LBEI63",
    "period": "2021-01-01T00:00:00/2022-01-01T00:00:00",
    "unit": "iso4217:ISK"
   }
  },
  "f6240": {
   "value": "9569608000",
   "decimals": -3,
   "dimensions": {
    "concept": "ifrs-full:ComprehensiveIncome",
    "entity": "scheme:213800R3IXBON2LBEI63",
    "period": "2021-01-01T00:00:00/2022-01-01T00:00:00",
    "ifrs-full:ComponentsOfEquityAxis": "ifrs-full:RetainedEarningsMember",
    "unit": "iso4217:ISK"
   }
  },
  "f6243": {
   "value": "9569608000",
   "decimals": -3,
   "dimensions": {
    "concept": "ifrs-full:ComprehensiveIncome",
    "entity": "scheme:213800R3IXBON2LBEI63",
    "period": "2021-01-01T00:00:00/2022-01-01T00:00:00",
    "unit": "iso4217:ISK"
   }
  },
  "f6248": {
   "value": "5891903000",
   "decimals": -3,
   "dimensions": {
    "concept": "SJ\u00d3:IncreaseDecreaseThroughTransfersRelatingToFinancialAssetsAtFairValueThroughProfitOrLoss",
    "entity": "scheme:213800R3IXBON2LBEI63",
    "period": "2021-01-01T00:00:00/2022-01-01T00:00:00",
    "ifrs-full:ComponentsOfEquityAxis": "ifrs-full:OtherReservesMember",
    "unit": "iso4217:ISK"
   }
  },
  "f6251": {
   "value": "-5891903000",
   "decimals": -3,
   "dimensions": {
    "concept": "SJ\u00d3:IncreaseDecreaseThroughTransfersRelatingToFinancialAssetsAtFairValueThroughProfitOrLoss",
    "entity": "scheme:213800R3IXBON2LBEI63",
    "period": "2021-01-01T00:00:00/2022-01-01T00:00:00",
    "ifrs-full:ComponentsOfEquityAxis": "ifrs-full:RetainedEarningsMember",
    "unit": "iso4217:ISK"
   }
  },
  "f6256": {
   "value": "97841000",
   "decimals": -3,
   "dimensions": {
    "concept": "SJ\u00d3:IncreaseDecreaseThroughTransfersRelatingToSubsidiaries",
    "entity": "scheme:213800R3IXBON2LBEI63",
    "period": "2021-01-01T00:00:00/2022-01-01T00:00:00",
    "ifrs-full:ComponentsOfEquityAxis": "ifrs-full:OtherReservesMember",
    "unit": "iso4217:ISK"
   }
  },
  "f6259": {
   "value": "-97841000",
   "decimals": -3,
   "dimensions": {
    "concept": "SJ\u00d3:IncreaseDecreaseThroughTransfersRelatingToSubsidiaries",
    "entity": "scheme:213800R3IXBON2LBEI63",
    "period": "2021-01-01T00:00:00/2022-01-01T00:00:00",
    "ifrs-full:ComponentsOfEquityAxis": "ifrs-full:RetainedEarningsMember",
    "unit": "iso4217:ISK"
   }
  },
  "f6265": {
   "value": "1227796000",
   "decimals": -3,
   "dimensions": {
    "concept": "ifrs-full:Equity",
    "entity": "scheme:213800R3IXBON2LBEI63",
    "period": "2022-01-01T00:00:00",
    "ifrs-full:ComponentsOfEquityAxis": "ifrs-full:IssuedCapitalMember",
    "unit": "iso4217:ISK"
   }
  },
  "f6268": {
   "value": "2274856000",
   "decimals": -3,
   "dimensions": {
    "concept": "ifrs-full:Equity",
    "entity": "scheme:213800R3IXBON2LBEI63",
    "period": "2022-01-01T00:00:00",
    "ifrs-full:ComponentsOfEquityAxis": "ifrs-full:SharePremiumMember",
    "unit": "iso4217:ISK"
   }
  },
  "f6271": {
   "value": "6722578000",
   "decimals": -3,
   "dimensions": {
    "concept": "ifrs-full:Equity",
    "entity": "scheme:213800R3IXBON2LBEI63",
    "period": "2022-01-01T00:00:00",
    "ifrs-full:ComponentsOfEquityAxis": "ifrs-full:OtherReservesMember",
    "unit": "iso4217:ISK"
   }
  },
  "f6274": {
   "value": "14113559000",
   "decimals": -3,
   "dimensions": {
    "concept": "ifrs-full:Equity",
    "entity": "scheme:213800R3IXBON2LBEI63",
    "period": "2022-01-01T00:00:00",
    "ifrs-full:ComponentsOfEquityAxis": "ifrs-full:RetainedEarningsMember",
    "unit": "iso4217:ISK"
   }
  },
  "f6277": {
   "value": "24338788000",
   "decimals": -3,
   "dimensions": {
    "concept": "ifrs-full:Equity",
    "entity": "scheme:213800R3IXBON2LBEI63",
    "period": "2022-01-01T00:00:00",
    "unit": "iso4217:ISK"
   }
  },
  "f6283": {
   "value": "1346607000",
   "decimals": -3,
   "dimensions": {
    "concept": "ifrs-full:Equity",
    "entity": "scheme:213800R3IXBON2LBEI63",
    "period": "2020-01-01T00:00:00",
    "ifrs-full:ComponentsOfEquityAxis": "ifrs-full:IssuedCapitalMember",
    "unit": "iso4217:ISK"
   }
  },
  "f6286": {
   "value": "6348500000",
   "decimals": -3,
   "dimensions": {
    "concept": "ifrs-full:Equity",
    "entity": "scheme:213800R3IXBON2LBEI63",
    "period": "2020-01-01T00:00:00",
    "ifrs-full:ComponentsOfEquityAxis": "ifrs-full:SharePremiumMember",
    "unit": "iso4217:ISK"
   }
  },
  "f6289": {
   "value": "990758000",
   "decimals": -3,
   "dimensions": {
    "concept": "ifrs-full:Equity",
    "entity": "scheme:213800R3IXBON2LBEI63",
    "period": "2020-01-01T00:00:00",
    "ifrs-full:ComponentsOfEquityAxis": "ifrs-full:OtherReservesMember",
    "unit": "iso4217:ISK"
   }
  },
  "f6292": {
   "value": "7608083000",
   "decimals": -3,
   "dimensions": {
    "concept": "ifrs-full:Equity",
    "entity": "scheme:213800R3IXBON2LBEI63",
    "period": "2020-01-01T00:00:00",
    "ifrs-full:ComponentsOfEquityAxis": "ifrs-full:RetainedEarningsMember",
    "unit": "iso4217:ISK"
   }
  },
  "f6295": {
   "value": "16293948000",
   "decimals": -3,
   "dimensions": {
    "concept": "ifrs-full:Equity",
    "entity": "scheme:213800R3IXBON2LBEI63",
    "period": "2020-01-01T00:00:00",
    "unit": "iso4217:ISK"
   }
  },
  "f6299": {
   "value": "12501000",
   "decimals": -3,
   "dimensions": {
    "concept": "ifrs-full:PurchaseOfTreasuryShares",
    "entity": "scheme:213800R3IXBON2LBEI63",
    "period": "2020-01-01T00:00:00/2021-01-01T00:00:00",
    "ifrs-full:ComponentsOfEquityAxis": "ifrs-full:IssuedCapitalMember",
    "unit": "iso4217:ISK"
   }
  },
  "f6304": {
   "value": "237874000",
   "decimals": -3,
   "dimensions": {
    "concept": "ifrs-full:PurchaseOfTreasuryShares",
    "entity": "scheme:213800R3IXBON2LBEI63",
    "period": "2020-01-01T00:00:00/2021-01-01T00:00:00",
    "ifrs-full:ComponentsOfEquityAxis": "ifrs-full:SharePremiumMember",
    "unit": "iso4217:ISK"
   }
  },
  "f6308": {
   "value": "250375000",
   "decimals": -3,
   "dimensions": {
    "concept": "ifrs-full:PurchaseOfTreasuryShares",
    "entity": "scheme:213800R3IXBON2LBEI63",
    "period": "2020-01-01T00:00:00/2021-01-01T00:00:00",
    "unit": "iso4217:ISK"
   }
  },
  "f6313": {
   "value": "5319986000",
   "decimals": -3,
   "dimensions": {
    "concept": "ifrs-full:ComprehensiveIncome",
    "entity": "scheme:213800R3IXBON2LBEI63",
    "period": "2020-01-01T00:00:00/2021-01-01T00:00:00",
    "ifrs-full:ComponentsOfEquityAxis": "ifrs-full:RetainedEarningsMember",
    "unit": "iso4217:ISK"
   }
  },
  "f6316": {
   "value": "5319986000",
   "decimals": -3,
   "dimensions": {
    "concept": "ifrs-full:ComprehensiveIncome",
    "entity": "scheme:213800R3IXBON2LBEI63",
    "period": "2020-01-01T00:00:00/2021-01-01T00:00:00",
    "unit": "iso4217:ISK"
   }
  },
  "f6321": {
   "value": "-257983000",
   "decimals": -3,
   "dimensions": {
    "concept": "SJ\u00d3:IncreaseDecreaseThroughTransfersRelatingToFinancialAssetsAtFairValueThroughProfitOrLoss",
    "entity": "scheme:213800R3IXBON2LBEI63",
    "period": "2020-01-01T00:00:00/2021-01-01T00:00:00",
    "ifrs-full:ComponentsOfEquityAxis": "ifrs-full:OtherReservesMember",
    "unit": "iso4217:ISK"
   }
  },
  "f6325": {
   "value": "257983000",
   "decimals": -3,
   "dimensions": {
    "concept": "SJ\u00d3:IncreaseDecreaseThroughTransfersRelatingToFinancialAssetsAtFairValueThroughProfitOrLoss",
    "entity": "scheme:213800R3IXBON2LBEI63",
    "period": "2020-01-01T00:00:00/2021-01-01T00:00:00",
    "ifrs-full:ComponentsOfEquityAxis": "ifrs-full:RetainedEarningsMember",
    "unit": "iso4217:ISK"
   }
  },
  "f6329": {
   "value": "59000",
   "decimals": -3,
   "dimensions": {
    "concept": "SJ\u00d3:IncreaseDecreaseThroughTransfersRelatingToSubsidiaries",
    "entity": "scheme:213800R3IXBON2LBEI63",
    "period": "2020-01-01T00:00:00/2021-01-01T00:00:00",
    "ifrs-full:ComponentsOfEquityAxis": "ifrs-full:OtherReservesMember",
    "unit": "iso4217:ISK"
   }
  },
  "f6332": {
   "value": "-59000",
   "decimals": -3,
   "dimensions": {
    "concept": "SJ\u00d3:IncreaseDecreaseThroughTransfersRelatingToSubsidiaries",
    "entity": "scheme:213800R3IXBON2LBEI63",
    "period": "2020-01-01T00:00:00/2021-01-01T00:00:00",
    "ifrs-full:ComponentsOfEquityAxis": "ifrs-full:RetainedEarningsMember",
    "unit": "iso4217:ISK"
   }
  },
  "f6339": {
   "value": "1334106000",
   "decimals": -3,
   "dimensions": {
    "concept": "ifrs-full:Equity",
    "entity": "scheme:213800R3IXBON2LBEI63",
    "period": "2021-01-01T00:00:00",
    "ifrs-full:ComponentsOfEquityAxis": "ifrs-full:IssuedCapitalMember",
    "unit": "iso4217:ISK"
   }
  },
  "f6342": {
   "value": "6110625000",
   "decimals": -3,
   "dimensions": {
    "concept": "ifrs-full:Equity",
    "entity": "scheme:213800R3IXBON2LBEI63",
    "period": "2021-01-01T00:00:00",
    "ifrs-full:ComponentsOfEquityAxis": "ifrs-full:SharePremiumMember",
    "unit": "iso4217:ISK"
   }
  },
  "f6345": {
   "value": "732834000",
   "decimals": -3,
   "dimensions": {
    "concept": "ifrs-full:Equity",
    "entity": "scheme:213800R3IXBON2LBEI63",
    "period": "2021-01-01T00:00:00",
    "ifrs-full:ComponentsOfEquityAxis": "ifrs-full:OtherReservesMember",
    "unit": "iso4217:ISK"
   }
  },
  "f6348": {
   "value": "13185993000",
   "decimals": -3,
   "dimensions": {
    "concept": "ifrs-full:Equity",
    "entity": "scheme:213800R3IXBON2LBEI63",
    "period": "2021-01-01T00:00:00",
    "ifrs-full:ComponentsOfEquityAxis": "ifrs-full:RetainedEarningsMember",
    "unit": "iso4217:ISK"
   }
  },
  "f6352": {
   "value": "21363559000",
   "decimals": -3,
   "dimensions": {
    "concept": "ifrs-full:Equity",
    "entity": "scheme:213800R3IXBON2LBEI63",
    "period": "2021-01-01T00:00:00",
    "unit": "iso4217:ISK"
   }
  },
  "f6441": {
   "value": "9569608000",
   "decimals": -3,
   "dimensions": {
    "concept": "ifrs-full:ComprehensiveIncome",
    "entity": "scheme:213800R3IXBON2LBEI63",
    "period": "2021-01-01T00:00:00/2022-01-01T00:00:00",
    "unit": "iso4217:ISK"
   }
  },
  "f6444": {
   "value": "5319986000",
   "decimals": -3,
   "dimensions": {
    "concept": "ifrs-full:ComprehensiveIncome",
    "entity": "scheme:213800R3IXBON2LBEI63",
    "period": "2020-01-01T00:00:00/2021-01-01T00:00:00",
    "unit": "iso4217:ISK"
   }
  },
  "f6451": {
   "value": "496659000",
   "decimals": -3,
   "dimensions": {
    "concept": "ifrs-full:AdjustmentsForFinanceIncome",
    "entity": "scheme:213800R3IXBON2LBEI63",
    "period": "2021-01-01T00:00:00/2022-01-01T00:00:00",
    "unit": "iso4217:ISK"
   }
  },
  "f6456": {
   "value": "479566000",
   "decimals": -3,
   "dimensions": {
    "concept": "ifrs-full:AdjustmentsForFinanceIncome",
    "entity": "scheme:213800R3IXBON2LBEI63",
    "period": "2020-01-01T00:00:00/2021-01-01T00:00:00",
    "unit": "iso4217:ISK"
   }
  },
  "f6461": {
   "value": "7887528000",
   "decimals": -3,
   "dimensions": {
    "concept": "SJ\u00d3:AdjustmentsForGainsLossesOnFinancialAssetsAtFairValueThroughProfitOrLoss",
    "entity": "scheme:213800R3IXBON2LBEI63",
    "period": "2021-01-01T00:00:00/2022-01-01T00:00:00",
    "unit": "iso4217:ISK"
   }
  },
  "f6466": {
   "value": "4798578000",
   "decimals": -3,
   "dimensions": {
    "concept": "SJ\u00d3:AdjustmentsForGainsLossesOnFinancialAssetsAtFairValueThroughProfitOrLoss",
    "entity": "scheme:213800R3IXBON2LBEI63",
    "period": "2020-01-01T00:00:00/2021-01-01T00:00:00",
    "unit": "iso4217:ISK"
   }
  },
  "f6472": {
   "value": "172336000",
   "decimals": -3,
   "dimensions": {
    "concept": "ifrs-full:AdjustmentsForDepreciationExpense",
    "entity": "scheme:213800R3IXBON2LBEI63",
    "period": "2021-01-01T00:00:00/2022-01-01T00:00:00",
    "unit": "iso4217:ISK"
   }
  },
  "f6475": {
   "value": "221613000",
   "decimals": -3,
   "dimensions": {
    "concept": "ifrs-full:AdjustmentsForDepreciationExpense",
    "entity": "scheme:213800R3IXBON2LBEI63",
    "period": "2020-01-01T00:00:00/2021-01-01T00:00:00",
    "unit": "iso4217:ISK"
   }
  },
  "f6479": {
   "value": "848000",
   "decimals": -3,
   "dimensions": {
    "concept": "ifrs-full:AdjustmentsForAmortisationExpense",
    "entity": "scheme:213800R3IXBON2LBEI63",
    "period": "2021-01-01T00:00:00/2022-01-01T00:00:00",
    "unit": "iso4217:ISK"
   }
  },
  "f6483": {
   "value": "1035000",
   "decimals": -3,
   "dimensions": {
    "concept": "ifrs-full:AdjustmentsForAmortisationExpense",
    "entity": "scheme:213800R3IXBON2LBEI63",
    "period": "2020-01-01T00:00:00/2021-01-01T00:00:00",
    "unit": "iso4217:ISK"
   }
  },
  "f6487": {
   "value": "449000",
   "decimals": -3,
   "dimensions": {
    "concept": "ifrs-full:AdjustmentsForLossesGainsOnDisposalOfNoncurrentAssets",
    "entity": "scheme:213800R3IXBON2LBEI63",
    "period": "2021-01-01T00:00:00/2022-01-01T00:00:00",
    "unit": "iso4217:ISK"
   }
  },
  "f6490": {
   "value": "0",
   "decimals": -3,
   "dimensions": {
    "concept": "ifrs-full:AdjustmentsForLossesGainsOnDisposalOfNoncurrentAssets",
    "entity": "scheme:213800R3IXBON2LBEI63",
    "period": "2020-01-01T00:00:00/2021-01-01T00:00:00",
    "unit": "iso4217:ISK"
   }
  },
  "f6493": {
   "value": "1359054000",
   "decimals": -3,
   "dimensions": {
    "concept": "ifrs-full:CashFlowsFromUsedInOperationsBeforeChangesInWorkingCapital",
    "entity": "scheme:213800R3IXBON2LBEI63",
    "period": "2021-01-01T00:00:00/2022-01-01T00:00:00",
    "unit": "iso4217:ISK"
   }
  },
  "f6496": {
   "value": "264490000",
   "decimals": -3,
   "dimensions": {
    "concept": "ifrs-full:CashFlowsFromUsedInOperationsBeforeChangesInWorkingCapital",
    "entity": "scheme:213800R3IXBON2LBEI63",
    "period": "2020-01-01T00:00:00/2021-01-01T00:00:00",
    "unit": "iso4217:ISK"
   }
  },
  "f6503": {
   "value": "-130131000",
   "decimals": -3,
   "dimensions": {
    "concept": "SJ\u00d3:AdjustmentsForDecreaseIncreaseInFinancialAssetsAtFairValueThroughProfitOrLoss",
    "entity": "scheme:213800R3IXBON2LBEI63",
    "period": "2021-01-01T00:00:00/2022-01-01T00:00:00",
    "unit": "iso4217:ISK"
   }
  },
  "f6508": {
   "value": "-4672616000",
   "decimals": -3,
   "dimensions": {
    "concept": "SJ\u00d3:AdjustmentsForDecreaseIncreaseInFinancialAssetsAtFairValueThroughProfitOrLoss",
    "entity": "scheme:213800R3IXBON2LBEI63",
    "period": "2020-01-01T00:00:00/2021-01-01T00:00:00",
    "unit": "iso4217:ISK"
   }
  },
  "f6513": {
   "value": "130000",
   "decimals": -3,
   "dimensions": {
    "concept": "SJ\u00d3:AdjustmentsForDecreaseIncreaseInDeferredTaxAssets",
    "entity": "scheme:213800R3IXBON2LBEI63",
    "period": "2021-01-01T00:00:00/2022-01-01T00:00:00",
    "unit": "iso4217:ISK"
   }
  },
  "f6516": {
   "value": "312000",
   "decimals": -3,
   "dimensions": {
    "concept": "SJ\u00d3:AdjustmentsForDecreaseIncreaseInDeferredTaxAssets",
    "entity": "scheme:213800R3IXBON2LBEI63",
    "period": "2020-01-01T00:00:00/2021-01-01T00:00:00",
    "unit": "iso4217:ISK"
   }
  },
  "f6519": {
   "value": "333770000",
   "decimals": -3,
   "dimensions": {
    "concept": "SJ\u00d3:AdjustmentsForDecreaseIncreaseInReinsuranceAssets",
    "entity": "scheme:213800R3IXBON2LBEI63",
    "period": "2021-01-01T00:00:00/2022-01-01T00:00:00",
    "unit": "iso4217:ISK"
   }
  },
  "f6522": {
   "value": "148716000",
   "decimals": -3,
   "dimensions": {
    "concept": "SJ\u00d3:AdjustmentsForDecreaseIncreaseInReinsuranceAssets",
    "entity": "scheme:213800R3IXBON2LBEI63",
    "period": "2020-01-01T00:00:00/2021-01-01T00:00:00",
    "unit": "iso4217:ISK"
   }
  },
  "f6525": {
   "value": "-183922000",
   "decimals": -3,
   "dimensions": {
    "concept": "ifrs-full:AdjustmentsForDecreaseIncreaseInTradeAccountReceivable",
    "entity": "scheme:213800R3IXBON2LBEI63",
    "period": "2021-01-01T00:00:00/2022-01-01T00:00:00",
    "unit": "iso4217:ISK"
   }
  },
  "f6530": {
   "value": "-265461000",
   "decimals": -3,
   "dimensions": {
    "concept": "ifrs-full:AdjustmentsForDecreaseIncreaseInTradeAccountReceivable",
    "entity": "scheme:213800R3IXBON2LBEI63",
    "period": "2020-01-01T00:00:00/2021-01-01T00:00:00",
    "unit": "iso4217:ISK"
   }
  },
  "f6535": {
   "value": "3474744000",
   "decimals": -3,
   "dimensions": {
    "concept": "SJ\u00d3:AdjustmentsForIncreaseDecreaseInLiabilitiesArisingFromInsuranceContracts",
    "entity": "scheme:213800R3IXBON2LBEI63",
    "period": "2021-01-01T00:00:00/2022-01-01T00:00:00",
    "unit": "iso4217:ISK"
   }
  },
  "f6538": {
   "value": "2267483000",
   "decimals": -3,
   "dimensions": {
    "concept": "SJ\u00d3:AdjustmentsForIncreaseDecreaseInLiabilitiesArisingFromInsuranceContracts",
    "entity": "scheme:213800R3IXBON2LBEI63",
    "period": "2020-01-01T00:00:00/2021-01-01T00:00:00",
    "unit": "iso4217:ISK"
   }
  },
  "f6541": {
   "value": "960263000",
   "decimals": -3,
   "dimensions": {
    "concept": "ifrs-full:AdjustmentsForIncreaseDecreaseInTradeAndOtherPayables",
    "entity": "scheme:213800R3IXBON2LBEI63",
    "period": "2021-01-01T00:00:00/2022-01-01T00:00:00",
    "unit": "iso4217:ISK"
   }
  },
  "f6544": {
   "value": "846499000",
   "decimals": -3,
   "dimensions": {
    "concept": "ifrs-full:AdjustmentsForIncreaseDecreaseInTradeAndOtherPayables",
    "entity": "scheme:213800R3IXBON2LBEI63",
    "period": "2020-01-01T00:00:00/2021-01-01T00:00:00",
    "unit": "iso4217:ISK"
   }
  },
  "f6547": {
   "value": "-4454854000",
   "decimals": -3,
   "dimensions": {
    "concept": "ifrs-full:IncreaseDecreaseInWorkingCapital",
    "entity": "scheme:213800R3IXBON2LBEI63",
    "period": "2021-01-01T00:00:00/2022-01-01T00:00:00",
    "unit": "iso4217:ISK"
   }
  },
  "f6550": {
   "value": "1675067000",
   "decimals": -3,
   "dimensions": {
    "concept": "ifrs-full:IncreaseDecreaseInWorkingCapital",
    "entity": "scheme:213800R3IXBON2LBEI63",
    "period": "2020-01-01T00:00:00/2021-01-01T00:00:00",
    "unit": "iso4217:ISK"
   }
  },
  "f6555": {
   "value": "1507892000",
   "decimals": -3,
   "dimensions": {
    "concept": "ifrs-full:FinanceIncomeReceivedClassifiedAsOperatingActivities",
    "entity": "scheme:213800R3IXBON2LBEI63",
    "period": "2021-01-01T00:00:00/2022-01-01T00:00:00",
    "unit": "iso4217:ISK"
   }
  },
  "f6558": {
   "value": "2731937000",
   "decimals": -3,
   "dimensions": {
    "concept": "ifrs-full:FinanceIncomeReceivedClassifiedAsOperatingActivities",
    "entity": "scheme:213800R3IXBON2LBEI63",
    "period": "2020-01-01T00:00:00/2021-01-01T00:00:00",
    "unit": "iso4217:ISK"
   }
  },
  "f6561": {
   "value": "604195000",
   "decimals": -3,
   "dimensions": {
    "concept": "SJ\u00d3:IncomeAndSpecialFinancialManagementTaxesPaidClassifiedAsOperatingActivities",
    "entity": "scheme:213800R3IXBON2LBEI63",
    "period": "2021-01-01T00:00:00/2022-01-01T00:00:00",
    "unit": "iso4217:ISK"
   }
  },
  "f6566": {
   "value": "556409000",
   "decimals": -3,
   "dimensions": {
    "concept": "SJ\u00d3:IncomeAndSpecialFinancialManagementTaxesPaidClassifiedAsOperatingActivities",
    "entity": "scheme:213800R3IXBON2LBEI63",
    "period": "2020-01-01T00:00:00/2021-01-01T00:00:00",
    "unit": "iso4217:ISK"
   }
  },
  "f6571": {
   "value": "6717605000",
   "decimals": -3,
   "dimensions": {
    "concept": "ifrs-full:CashFlowsFromUsedInOperatingActivities",
    "entity": "scheme:213800R3IXBON2LBEI63",
    "period": "2021-01-01T00:00:00/2022-01-01T00:00:00",
    "unit": "iso4217:ISK"
   }
  },
  "f6574": {
   "value": "764951000",
   "decimals": -3,
   "dimensions": {
    "concept": "ifrs-full:CashFlowsFromUsedInOperatingActivities",
    "entity": "scheme:213800R3IXBON2LBEI63",
    "period": "2020-01-01T00:00:00/2021-01-01T00:00:00",
    "unit": "iso4217:ISK"
   }
  },
  "f6579": {
   "value": "54125000",
   "decimals": -3,
   "dimensions": {
    "concept": "ifrs-full:PurchaseOfPropertyPlantAndEquipmentClassifiedAsInvestingActivities",
    "entity": "scheme:213800R3IXBON2LBEI63",
    "period": "2021-01-01T00:00:00/2022-01-01T00:00:00",
    "unit": "iso4217:ISK"
   }
  },
  "f6584": {
   "value": "179639000",
   "decimals": -3,
   "dimensions": {
    "concept": "ifrs-full:PurchaseOfPropertyPlantAndEquipmentClassifiedAsInvestingActivities",
    "entity": "scheme:213800R3IXBON2LBEI63",
    "period": "2020-01-01T00:00:00/2021-01-01T00:00:00",
    "unit": "iso4217:ISK"
   }
  },
  "f6589": {
   "value": "3914000",
   "decimals": -3,
   "dimensions": {
    "concept": "ifrs-full:ProceedsFromSalesOfPropertyPlantAndEquipmentClassifiedAsInvestingActivities",
    "entity": "scheme:213800R3IXBON2LBEI63",
    "period": "2021-01-01T00:00:00/2022-01-01T00:00:00",
    "unit": "iso4217:ISK"
   }
  },
  "f6593": {
   "value": "0",
   "decimals": -3,
   "dimensions": {
    "concept": "ifrs-full:ProceedsFromSalesOfPropertyPlantAndEquipmentClassifiedAsInvestingActivities",
    "entity": "scheme:213800R3IXBON2LBEI63",
    "period": "2020-01-01T00:00:00/2021-01-01T00:00:00",
    "unit": "iso4217:ISK"
   }
  },
  "f6598": {
   "value": "-50211000",
   "decimals": -3,
   "dimensions": {
    "concept": "ifrs-full:CashFlowsFromUsedInInvestingActivities",
    "entity": "scheme:213800R3IXBON2LBEI63",
    "period": "2021-01-01T00:00:00/2022-01-01T00:00:00",
    "unit": "iso4217:ISK"
   }
  },
  "f6603": {
   "value": "-179639000",
   "decimals": -3,
   "dimensions": {
    "concept": "ifrs-full:CashFlowsFromUsedInInvestingActivities",
    "entity": "scheme:213800R3IXBON2LBEI63",
    "period": "2020-01-01T00:00:00/2021-01-01T00:00:00",
    "unit": "iso4217:ISK"
   }
  },
  "f6608": {
   "value": "2652298000",
   "decimals": -3,
   "dimensions": {
    "concept": "ifrs-full:DividendsPaidClassifiedAsFinancingActivities",
    "entity": "scheme:213800R3IXBON2LBEI63",
    "period": "2021-01-01T00:00:00/2022-01-01T00:00:00",
    "unit": "iso4217:ISK"
   }
  },
  "f6614": {
   "value": "0",
   "decimals": -3,
   "dimensions": {
    "concept": "ifrs-full:DividendsPaidClassifiedAsFinancingActivities",
    "entity": "scheme:213800R3IXBON2LBEI63",
    "period": "2020-01-01T00:00:00/2021-01-01T00:00:00",
    "unit": "iso4217:ISK"
   }
  },
  "f6617": {
   "value": "1442081000",
   "decimals": -3,
   "dimensions": {
    "concept": "ifrs-full:PaymentsToAcquireOrRedeemEntitysShares",
    "entity": "scheme:213800R3IXBON2LBEI63",
    "period": "2021-01-01T00:00:00/2022-01-01T00:00:00",
    "unit": "iso4217:ISK"
   }
  },
  "f6622": {
   "value": "250375000",
   "decimals": -3,
   "dimensions": {
    "concept": "ifrs-full:PaymentsToAcquireOrRedeemEntitysShares",
    "entity": "scheme:213800R3IXBON2LBEI63",
    "period": "2020-01-01T00:00:00/2021-01-01T00:00:00",
    "unit": "iso4217:ISK"
   }
  },
  "f6627": {
   "value": "2500000000",
   "decimals": -3,
   "dimensions": {
    "concept": "SJ\u00d3:ReductionOfIssuedCapitalClassifiedAsFinancingActivities",
    "entity": "scheme:213800R3IXBON2LBEI63",
    "period": "2021-01-01T00:00:00/2022-01-01T00:00:00",
    "unit": "iso4217:ISK"
   }
  },
  "f6633": {
   "value": "0",
   "decimals": -3,
   "dimensions": {
    "concept": "SJ\u00d3:ReductionOfIssuedCapitalClassifiedAsFinancingActivities",
    "entity": "scheme:213800R3IXBON2LBEI63",
    "period": "2020-01-01T00:00:00/2021-01-01T00:00:00",
    "unit": "iso4217:ISK"
   }
  },
  "f6636": {
   "value": "141529000",
   "decimals": -3,
   "dimensions": {
    "concept": "ifrs-full:PaymentsOfLeaseLiabilitiesClassifiedAsFinancingActivities",
    "entity": "scheme:213800R3IXBON2LBEI63",
    "period": "2021-01-01T00:00:00/2022-01-01T00:00:00",
    "unit": "iso4217:ISK"
   }
  },
  "f6641": {
   "value": "147955000",
   "decimals": -3,
   "dimensions": {
    "concept": "ifrs-full:PaymentsOfLeaseLiabilitiesClassifiedAsFinancingActivities",
    "entity": "scheme:213800R3IXBON2LBEI63",
    "period": "2020-01-01T00:00:00/2021-01-01T00:00:00",
    "unit": "iso4217:ISK"
   }
  },
  "f6648": {
   "value": "-6735908000",
   "decimals": -3,
   "dimensions": {
    "concept": "ifrs-full:CashFlowsFromUsedInFinancingActivities",
    "entity": "scheme:213800R3IXBON2LBEI63",
    "period": "2021-01-01T00:00:00/2022-01-01T00:00:00",
    "unit": "iso4217:ISK"
   }
  },
  "f6653": {
   "value": "-398330000",
   "decimals": -3,
   "dimensions": {
    "concept": "ifrs-full:CashFlowsFromUsedInFinancingActivities",
    "entity": "scheme:213800R3IXBON2LBEI63",
    "period": "2020-01-01T00:00:00/2021-01-01T00:00:00",
    "unit": "iso4217:ISK"
   }
  },
  "f6659": {
   "value": "-68514000",
   "decimals": -3,
   "dimensions": {
    "concept": "ifrs-full:IncreaseDecreaseInCashAndCashEquivalentsBeforeEffectOfExchangeRateChanges",
    "entity": "scheme:213800R3IXBON2LBEI63",
    "period": "2021-01-01T00:00:00/2022-01-01T00:00:00",
    "unit": "iso4217:ISK"
   }
  },
  "f6664": {
   "value": "186982000",
   "decimals": -3,
   "dimensions": {
    "concept": "ifrs-full:IncreaseDecreaseInCashAndCashEquivalentsBeforeEffectOfExchangeRateChanges",
    "entity": "scheme:213800R3IXBON2LBEI63",
    "period": "2020-01-01T00:00:00/2021-01-01T00:00:00",
    "unit": "iso4217:ISK"
   }
  },
  "f6668": {
   "value": "3187000",
   "decimals": -3,
   "dimensions": {
    "concept": "ifrs-full:EffectOfExchangeRateChangesOnCashAndCashEquivalents",
    "entity": "scheme:213800R3IXBON2LBEI63",
    "period": "2021-01-01T00:00:00/2022-01-01T00:00:00",
    "unit": "iso4217:ISK"
   }
  },
  "f6671": {
   "value": "3788000",
   "decimals": -3,
   "dimensions": {
    "concept": "ifrs-full:EffectOfExchangeRateChangesOnCashAndCashEquivalents",
    "entity": "scheme:213800R3IXBON2LBEI63",
    "period": "2020-01-01T00:00:00/2021-01-01T00:00:00",
    "unit": "iso4217:ISK"
   }
  },
  "f6675": {
   "value": "1160223000",
   "decimals": -3,
   "dimensions": {
    "concept": "ifrs-full:CashAndCashEquivalents",
    "entity": "scheme:213800R3IXBON2LBEI63",
    "period": "2021-01-01T00:00:00",
    "unit": "iso4217:ISK"
   }
  },
  "f6678": {
   "value": "969453000",
   "decimals": -3,
   "dimensions": {
    "concept": "ifrs-full:CashAndCashEquivalents",
    "entity": "scheme:213800R3IXBON2LBEI63",
    "period": "2020-01-01T00:00:00",
    "unit": "iso4217:ISK"
   }
  },
  "f6682": {
   "value": "1094896000",
   "decimals": -3,
   "dimensions": {
    "concept": "ifrs-full:CashAndCashEquivalents",
    "entity": "scheme:213800R3IXBON2LBEI63",
    "period": "2022-01-01T00:00:00",
    "unit": "iso4217:ISK"
   }
  },
  "f6685": {
   "value": "1160223000",
   "decimals": -3,
   "dimensions": {
    "concept": "ifrs-full:CashAndCashEquivalents",
    "entity": "scheme:213800R3IXBON2LBEI63",
    "period": "2021-01-01T00:00:00",
    "unit": "iso4217:ISK"
   }
  },
  "f6904": {
   "value": "hlutaf\u00e9lag",
   "dimensions": {
    "concept": "ifrs-full:LegalFormOfEntity",
    "language": "is",
    "entity": "scheme:213800R3IXBON2LBEI63",
    "period": "2021-01-01T00:00:00/2022-01-01T00:00:00"
   }
  },
  "f6914": {
   "value": "\u00cdsland",
   "dimensions": {
    "concept": "ifrs-full:DomicileOfEntity",
    "language": "is",
    "entity": "scheme:213800R3IXBON2LBEI63",
    "period": "2021-01-01T00:00:00/2022-01-01T00:00:00"
   }
  },
  "pp-value-9": {
   "value": "Kringlunni 5",
   "dimensions": {
    "concept": "ifrs-full:PrincipalPlaceOfBusiness",
    "language": "is",
    "entity": "scheme:213800R3IXBON2LBEI63",
    "period": "2021-01-01T00:00:00/2022-01-01T00:00:00"
   }
  }
 }
}